[
  {
    "symbol": "AUB",
    "displayName": "AUB GROUP LIMITED",
    "industry": "Insurance",
    "dateListed": "2005-11-16",
    "marketCap": 2636747552,
    "xid": "3582563",
    "priceChangeFiveDayPercent": 3.2374100719424552,
    "isRecentListing": false,
    "priceAsk": 25.830000000000002,
    "priceBid": 25.72,
    "priceChange": -0.13999999999999702,
    "priceChangePercent": -0.539083557951471,
    "priceLast": 25.830000000000002,
    "sector": "Financials",
    "industryGroup": "Insurance",
    "securityType": 1,
    "volume": 254170,
    "statusCode": "",
    "isin": "AU000000AUB9",
    "priceClose": 25.97,
    "priceDayHigh": 26.16,
    "priceDayLow": 25.73,
    "priceFiftyTwoWeekHigh": 26.35,
    "priceFiftyTwoWeekLow": 16.23,
    "volumeAverage": 213003.604396,
    "dateExDate": "2022-09-07",
    "datePayDate": "2022-10-07",
    "dateRecordDate": "2022-09-08",
    "dividend": 0.38,
    "dividendType": "F",
    "frankingPercent": 100,
    "cashFlow": 51.664,
    "earningsPerShare": 1.04945,
    "freeCashFlowYield": 0.047082996493729254,
    "priceEarningsRatio": 24.7463,
    "priceToCash": 21.23909,
    "foreignExempt": false,
    "shareDescription": "Ordinary Fully Paid",
    "numOfShares": 101530518,
    "yieldAnnual": 2.129307007355788,
    "incomeStatement": [
      {
        "revenue": 333537000,
        "netIncome": 80836000,
        "period": "2022A",
        "fPeriodEndDate": 44742,
        "curCode": "AUD"
      },
      {
        "revenue": 314368000,
        "netIncome": 70621000,
        "period": "2021A",
        "fPeriodEndDate": 44377,
        "curCode": "AUD"
      },
      {
        "revenue": 305784000,
        "netIncome": 46984000,
        "period": "2020A",
        "fPeriodEndDate": 44012,
        "curCode": "AUD"
      },
      {
        "revenue": 279811000,
        "netIncome": 48361000,
        "period": "2019A",
        "fPeriodEndDate": 43646,
        "curCode": "AUD"
      }
    ]
  },
  {
    "symbol": "ENA",
    "displayName": "ENSURANCE LTD",
    "industry": "Insurance",
    "dateListed": "2011-09-23",
    "marketCap": 22527484,
    "xid": "36099305",
    "priceChangeFiveDayPercent": 4.1666666666666705,
    "isRecentListing": false,
    "priceAsk": 0.255,
    "priceBid": 0.23,
    "priceChange": 0,
    "priceChangePercent": 0,
    "priceLast": 0.25,
    "sector": "Financials",
    "industryGroup": "Insurance",
    "securityType": 1,
    "volume": 39920,
    "statusCode": "",
    "isin": "AU000000ENA8",
    "priceClose": 0.25,
    "priceDayHigh": 0.25,
    "priceDayLow": 0.25,
    "priceFiftyTwoWeekHigh": 0.3,
    "priceFiftyTwoWeekLow": 0.2,
    "volumeAverage": 40472.575758,
    "cashFlow": 0.44354,
    "earningsPerShare": 0.00327,
    "freeCashFlowYield": 0.016128743501527633,
    "priceEarningsRatio": 76.4526,
    "priceToCash": 62.00111,
    "foreignExempt": false,
    "shareDescription": "Ordinary Fully Paid",
    "numOfShares": 90109937,
    "yieldAnnual": 0,
    "incomeStatement": [
      {
        "revenue": 7314440,
        "netIncome": 273750,
        "period": "2022A",
        "fPeriodEndDate": 44742,
        "curCode": "AUD"
      },
      {
        "revenue": 4359120,
        "netIncome": -1302840,
        "period": "2021A",
        "fPeriodEndDate": 44377,
        "curCode": "AUD"
      },
      {
        "revenue": 3711330,
        "netIncome": -2153770,
        "period": "2020A",
        "fPeriodEndDate": 44012,
        "curCode": "AUD"
      },
      {
        "revenue": 1397390,
        "netIncome": -1401740,
        "period": "2019A",
        "fPeriodEndDate": 43646,
        "curCode": "AUD"
      }
    ]
  },
  {
    "symbol": "GDG",
    "displayName": "GENERATION DEVELOPMENT GROUP LIMITED",
    "industry": "Insurance",
    "dateListed": "2007-12-11",
    "marketCap": 251999236,
    "xid": "9390150",
    "priceChangeFiveDayPercent": 0.3846153846153764,
    "isRecentListing": false,
    "priceAsk": 1.34,
    "priceBid": 1.3,
    "priceChange": -0.030000000000000027,
    "priceChangePercent": -2.247191011235957,
    "priceLast": 1.305,
    "sector": "Financials",
    "industryGroup": "Insurance",
    "securityType": 1,
    "volume": 9030,
    "statusCode": "",
    "isin": "AU0000005126",
    "priceClose": 1.335,
    "priceDayHigh": 1.34,
    "priceDayLow": 1.305,
    "priceFiftyTwoWeekHigh": 1.79,
    "priceFiftyTwoWeekLow": 1.1,
    "volumeAverage": 155751.216216,
    "dateExDate": "2022-09-09",
    "datePayDate": "2022-10-06",
    "dateRecordDate": "2022-09-12",
    "dividend": 0.01,
    "dividendType": "F",
    "frankingPercent": 100,
    "cashFlow": -0.223,
    "earningsPerShare": 0.01057,
    "freeCashFlowYield": -0.0000100000010000001,
    "priceEarningsRatio": 126.3008,
    "priceToCash": -99999.99,
    "foreignExempt": false,
    "shareDescription": "Ordinary Fully Paid",
    "numOfShares": 188763473,
    "yieldAnnual": 1.5325670498084292,
    "incomeStatement": [
      {
        "revenue": -176093000,
        "netIncome": 1901000,
        "period": "2022A",
        "fPeriodEndDate": 44742,
        "curCode": "AUD"
      },
      {
        "revenue": 267445000,
        "netIncome": 2533000,
        "period": "2021A",
        "fPeriodEndDate": 44377,
        "curCode": "AUD"
      },
      {
        "revenue": -28148000,
        "netIncome": -1637000,
        "period": "2020A",
        "fPeriodEndDate": 44012,
        "curCode": "AUD"
      },
      {
        "revenue": 82225000,
        "netIncome": 5286000,
        "period": "2019A",
        "fPeriodEndDate": 43646,
        "curCode": "AUD"
      }
    ]
  },
  {
    "symbol": "IAG",
    "displayName": "INSURANCE AUSTRALIA GROUP LIMITED",
    "industry": "Insurance",
    "dateListed": "2000-08-08",
    "marketCap": 11833060716,
    "xid": "151417",
    "priceChangeFiveDayPercent": -2.0325203252032447,
    "isRecentListing": false,
    "priceAsk": 4.8500000000000005,
    "priceBid": 4.79,
    "priceChange": -0.009999999999999787,
    "priceChangePercent": -0.20703933747411565,
    "priceLast": 4.82,
    "sector": "Financials",
    "industryGroup": "Insurance",
    "securityType": 1,
    "volume": 6779463,
    "statusCode": "XD",
    "isin": "AU000000IAG3",
    "priceClose": 4.83,
    "priceDayHigh": 4.8500000000000005,
    "priceDayLow": 4.7700000000000005,
    "priceFiftyTwoWeekHigh": 5.12,
    "priceFiftyTwoWeekLow": 4.02,
    "volumeAverage": 7172272.098901,
    "dateExDate": "2023-02-16",
    "datePayDate": "2023-03-23",
    "dateRecordDate": "2023-02-17",
    "dividend": 0.06,
    "dividendType": "I",
    "frankingPercent": 30,
    "cashFlow": 505,
    "earningsPerShare": 0.24354,
    "freeCashFlowYield": 0.07225517058000672,
    "priceEarningsRatio": 19.83247,
    "priceToCash": 13.83984,
    "foreignExempt": false,
    "shareDescription": "Ordinary Fully Paid",
    "numOfShares": 2449909051,
    "yieldAnnual": 2.2821576763485476,
    "incomeStatement": [
      {
        "revenue": 13913000000,
        "netIncome": 347000000,
        "period": "2022A",
        "fPeriodEndDate": 44742,
        "curCode": "AUD"
      },
      {
        "revenue": 13587000000,
        "netIncome": -427000000,
        "period": "2021A",
        "fPeriodEndDate": 44377,
        "curCode": "AUD"
      },
      {
        "revenue": 13417000000,
        "netIncome": 435000000,
        "period": "2020A",
        "fPeriodEndDate": 44012,
        "curCode": "AUD"
      },
      {
        "revenue": 13433000000,
        "netIncome": 1076000000,
        "period": "2019A",
        "fPeriodEndDate": 43646,
        "curCode": "AUD"
      }
    ]
  },
  {
    "symbol": "MPL",
    "displayName": "MEDIBANK PRIVATE LIMITED",
    "industry": "Insurance",
    "dateListed": "2014-11-25",
    "marketCap": 8592490109,
    "xid": "80536726",
    "priceChangeFiveDayPercent": -1.2903225806451624,
    "isRecentListing": false,
    "priceAsk": 3.08,
    "priceBid": 3.0500000000000003,
    "priceChange": -0.06000000000000005,
    "priceChangePercent": -1.9230769230769247,
    "priceLast": 3.06,
    "sector": "Financials",
    "industryGroup": "Insurance",
    "securityType": 1,
    "volume": 11626674,
    "statusCode": "",
    "isin": "AU000000MPL3",
    "priceClose": 3.12,
    "priceDayHigh": 3.105,
    "priceDayLow": 3.0100000000000002,
    "priceFiftyTwoWeekHigh": 3.785,
    "priceFiftyTwoWeekLow": 2.73,
    "volumeAverage": 11670028.905882,
    "dateExDate": "2022-09-07",
    "datePayDate": "2022-09-29",
    "dateRecordDate": "2022-09-08",
    "dividend": 0.073,
    "dividendType": "F",
    "frankingPercent": 100,
    "cashFlow": 555.4,
    "earningsPerShare": 0.14304,
    "freeCashFlowYield": 0.059226127724698006,
    "priceEarningsRatio": 21.81208,
    "priceToCash": 16.88444,
    "foreignExempt": false,
    "shareDescription": "Ordinary Fully Paid",
    "numOfShares": 2754003240,
    "yieldAnnual": 4.379084967320262,
    "incomeStatement": [
      {
        "revenue": 7108800000,
        "netIncome": 393900000,
        "period": "2022A",
        "fPeriodEndDate": 44742,
        "curCode": "AUD"
      },
      {
        "revenue": 7035100000,
        "netIncome": 441200000,
        "period": "2021A",
        "fPeriodEndDate": 44377,
        "curCode": "AUD"
      },
      {
        "revenue": 6776600000,
        "netIncome": 315000000,
        "period": "2020A",
        "fPeriodEndDate": 44012,
        "curCode": "AUD"
      },
      {
        "revenue": 6763200000,
        "netIncome": 458700000,
        "period": "2019A",
        "fPeriodEndDate": 43646,
        "curCode": "AUD"
      }
    ]
  },
  {
    "symbol": "NHF",
    "displayName": "NIB HOLDINGS LIMITED",
    "industry": "Insurance",
    "dateListed": "2007-11-05",
    "marketCap": 3832449878,
    "xid": "9141105",
    "priceChangeFiveDayPercent": -12.249999999999995,
    "isRecentListing": false,
    "priceAsk": 7.1000000000000005,
    "priceBid": 7.01,
    "priceChange": -0.9199999999999999,
    "priceChangePercent": -11.58690176322418,
    "priceLast": 7.0200000000000005,
    "sector": "Financials",
    "industryGroup": "Insurance",
    "securityType": 1,
    "volume": 3104711,
    "statusCode": "",
    "isin": "AU000000NHF0",
    "priceClose": 7.94,
    "priceDayHigh": 7.5,
    "priceDayLow": 6.88,
    "priceFiftyTwoWeekHigh": 8.195,
    "priceFiftyTwoWeekLow": 6.15,
    "volumeAverage": 1063072.9,
    "dateExDate": "2023-03-02",
    "datePayDate": "2023-04-03",
    "dateRecordDate": "2023-03-03",
    "dividend": 0.13,
    "dividendType": "I",
    "frankingPercent": 100,
    "cashFlow": 196.7,
    "earningsPerShare": 0.29607,
    "freeCashFlowYield": 0.04318385960063567,
    "priceEarningsRatio": 26.81798,
    "priceToCash": 23.1568,
    "foreignExempt": false,
    "shareDescription": "Ordinary Fully Paid",
    "numOfShares": 482676307,
    "yieldAnnual": 3.133903133903134,
    "incomeStatement": [
      {
        "revenue": 2715500000,
        "netIncome": 133800000,
        "period": "2022A",
        "fPeriodEndDate": 44742,
        "curCode": "AUD"
      },
      {
        "revenue": 2611400000,
        "netIncome": 160500000,
        "period": "2021A",
        "fPeriodEndDate": 44377,
        "curCode": "AUD"
      },
      {
        "revenue": 2509700000,
        "netIncome": 87000000,
        "period": "2020A",
        "fPeriodEndDate": 44012,
        "curCode": "AUD"
      },
      {
        "revenue": 2451500000,
        "netIncome": 149300000,
        "period": "2019A",
        "fPeriodEndDate": 43646,
        "curCode": "AUD"
      }
    ]
  },
  {
    "symbol": "NOL",
    "displayName": "NOBLEOAK LIFE LIMITED",
    "industry": "Insurance",
    "dateListed": "2021-07-22",
    "marketCap": 154727428,
    "xid": "667331428",
    "priceChangeFiveDayPercent": -2.702702702702705,
    "isRecentListing": false,
    "priceAsk": 1.83,
    "priceBid": 1.7,
    "priceChange": 0,
    "priceChangePercent": 0,
    "priceLast": 1.8,
    "sector": "Financials",
    "industryGroup": "Insurance",
    "securityType": 1,
    "volume": 8700,
    "statusCode": "",
    "isin": "AU0000161580",
    "priceClose": 1.8,
    "priceDayHigh": 1.8,
    "priceDayLow": 1.8,
    "priceFiftyTwoWeekHigh": 2.45,
    "priceFiftyTwoWeekLow": 1.5,
    "volumeAverage": 76092.886792,
    "cashFlow": 15.332,
    "earningsPerShare": 0.02245,
    "freeCashFlowYield": 0.021482941684984456,
    "priceEarningsRatio": 80.17817,
    "priceToCash": 46.54856,
    "foreignExempt": false,
    "shareDescription": "Ordinary Fully Paid",
    "numOfShares": 85959682,
    "yieldAnnual": 0,
    "incomeStatement": [
      {
        "revenue": 83401000,
        "netIncome": 1685000,
        "period": "2022A",
        "fPeriodEndDate": 44742,
        "curCode": "AUD"
      },
      {
        "revenue": 63494000,
        "netIncome": 4903000,
        "period": "2021A",
        "fPeriodEndDate": 44377,
        "curCode": "AUD"
      },
      {
        "revenue": 106556000,
        "netIncome": 7636000,
        "period": "2020A",
        "fPeriodEndDate": 44012,
        "curCode": "AUD"
      },
      {
        "revenue": 30253500,
        "netIncome": 5233390,
        "period": "2019A",
        "fPeriodEndDate": 43646,
        "curCode": "AUD"
      }
    ]
  },
  {
    "symbol": "PSI",
    "displayName": "PSC INSURANCE GROUP LIMITED",
    "industry": "Insurance",
    "dateListed": "2015-12-15",
    "marketCap": 1654257729,
    "xid": "320554376",
    "priceChangeFiveDayPercent": -1.6666666666666683,
    "isRecentListing": false,
    "priceAsk": 4.72,
    "priceBid": 4.61,
    "priceChange": 0.04999999999999982,
    "priceChangePercent": 1.0706638115631655,
    "priceLast": 4.72,
    "sector": "Financials",
    "industryGroup": "Insurance",
    "securityType": 1,
    "volume": 30879,
    "statusCode": "",
    "isin": "AU000000PSI6",
    "priceClose": 4.67,
    "priceDayHigh": 4.72,
    "priceDayLow": 4.68,
    "priceFiftyTwoWeekHigh": 5.3,
    "priceFiftyTwoWeekLow": 3.9,
    "volumeAverage": 63596.824176,
    "dateExDate": "2022-09-13",
    "datePayDate": "2022-10-12",
    "dateRecordDate": "2022-09-14",
    "dividend": 0.075,
    "dividendType": "F",
    "frankingPercent": 60,
    "cashFlow": 31.937,
    "earningsPerShare": 0.0789,
    "freeCashFlowYield": 0.028842540208664245,
    "priceEarningsRatio": 59.18885,
    "priceToCash": 34.67101,
    "foreignExempt": false,
    "shareDescription": "Ordinary Fully Paid",
    "numOfShares": 354230777,
    "yieldAnnual": 2.542372881355932,
    "incomeStatement": [
      {
        "revenue": 252768000,
        "netIncome": 26658000,
        "period": "2022A",
        "fPeriodEndDate": 44742,
        "curCode": "AUD"
      },
      {
        "revenue": 205840000,
        "netIncome": 40447000,
        "period": "2021A",
        "fPeriodEndDate": 44377,
        "curCode": "AUD"
      },
      {
        "revenue": 175669000,
        "netIncome": 17887000,
        "period": "2020A",
        "fPeriodEndDate": 44012,
        "curCode": "AUD"
      },
      {
        "revenue": 117238000,
        "netIncome": 24693000,
        "period": "2019A",
        "fPeriodEndDate": 43646,
        "curCode": "AUD"
      }
    ]
  },
  {
    "symbol": "QBE",
    "displayName": "QBE INSURANCE GROUP LIMITED",
    "industry": "Insurance",
    "dateListed": "1973-06-28",
    "marketCap": 21364938479,
    "xid": "237176",
    "priceChangeFiveDayPercent": 11.343283582089548,
    "isRecentListing": false,
    "priceAsk": 14.94,
    "priceBid": 14.88,
    "priceChange": 0.5299999999999994,
    "priceChangePercent": 3.6831132731063194,
    "priceLast": 14.92,
    "sector": "Financials",
    "industryGroup": "Insurance",
    "securityType": 1,
    "volume": 7184055,
    "statusCode": "CD",
    "isin": "AU000000QBE9",
    "priceClose": 14.39,
    "priceDayHigh": 14.950000000000001,
    "priceDayLow": 14.42,
    "priceFiftyTwoWeekHigh": 14.950000000000001,
    "priceFiftyTwoWeekLow": 10,
    "volumeAverage": 3881075.252747,
    "dateExDate": "2023-03-06",
    "datePayDate": "2023-04-14",
    "dateRecordDate": "2023-03-07",
    "dividend": 0.3,
    "dividendType": "F",
    "frankingPercent": 10,
    "cashFlow": 3362.411,
    "earningsPerShare": 0.70013,
    "freeCashFlowYield": 0.05908552156562452,
    "priceEarningsRatio": 20.55336,
    "priceToCash": 16.92462,
    "foreignExempt": false,
    "shareDescription": "Ordinary Fully Paid",
    "numOfShares": 1484707330,
    "yieldAnnual": 2.613941018766756,
    "incomeStatement": [
      {
        "revenue": 18250000000,
        "netIncome": 770000000,
        "period": "2022A",
        "fPeriodEndDate": 44926,
        "curCode": "USD"
      },
      {
        "revenue": 17261000000,
        "netIncome": 750000000,
        "period": "2021A",
        "fPeriodEndDate": 44561,
        "curCode": "USD"
      },
      {
        "revenue": 15747000000,
        "netIncome": -1517000000,
        "period": "2020A",
        "fPeriodEndDate": 44196,
        "curCode": "USD"
      },
      {
        "revenue": 14594000000,
        "netIncome": 550000000,
        "period": "2019A",
        "fPeriodEndDate": 43830,
        "curCode": "USD"
      }
    ]
  },
  {
    "symbol": "SDF",
    "displayName": "STEADFAST GROUP LIMITED",
    "industry": "Insurance",
    "dateListed": "2013-08-02",
    "marketCap": 5867874707,
    "xid": "59611073",
    "priceChangeFiveDayPercent": 4.444444444444431,
    "isRecentListing": false,
    "priceAsk": 5.7,
    "priceBid": 5.6000000000000005,
    "priceChange": -0.010000000000000675,
    "priceChangePercent": -0.1769911504424898,
    "priceLast": 5.64,
    "sector": "Financials",
    "industryGroup": "Insurance",
    "securityType": 1,
    "volume": 1689332,
    "statusCode": "",
    "isin": "AU000000SDF8",
    "priceClose": 5.65,
    "priceDayHigh": 5.655,
    "priceDayLow": 5.6000000000000005,
    "priceFiftyTwoWeekHigh": 5.74,
    "priceFiftyTwoWeekLow": 4.27,
    "volumeAverage": 2367268.10989,
    "dateExDate": "2022-08-22",
    "datePayDate": "2022-09-09",
    "dateRecordDate": "2022-08-23",
    "dividend": 0.078,
    "dividendType": "F",
    "frankingPercent": 100,
    "cashFlow": 131.3,
    "earningsPerShare": 0.18131,
    "freeCashFlowYield": 0.04744476717429404,
    "priceEarningsRatio": 31.1621,
    "priceToCash": 21.07714,
    "foreignExempt": false,
    "shareDescription": "Ordinary Fully Paid",
    "numOfShares": 1038561895,
    "yieldAnnual": 2.304964539007092,
    "incomeStatement": [
      {
        "revenue": 1129000000,
        "netIncome": 171600000,
        "period": "2022A",
        "fPeriodEndDate": 44742,
        "curCode": "AUD"
      },
      {
        "revenue": 902000000,
        "netIncome": 143000000,
        "period": "2021A",
        "fPeriodEndDate": 44377,
        "curCode": "AUD"
      },
      {
        "revenue": 814195000,
        "netIncome": -55244000,
        "period": "2020A",
        "fPeriodEndDate": 44012,
        "curCode": "AUD"
      },
      {
        "revenue": 681734000,
        "netIncome": 103845000,
        "period": "2019A",
        "fPeriodEndDate": 43646,
        "curCode": "AUD"
      }
    ]
  },
  {
    "symbol": "SUN",
    "displayName": "SUNCORP GROUP LIMITED",
    "industry": "Insurance",
    "dateListed": "1988-07-07",
    "marketCap": 16154886130,
    "xid": "262335",
    "priceChangeFiveDayPercent": -1.5372790161414243,
    "isRecentListing": false,
    "priceAsk": 12.82,
    "priceBid": 12.75,
    "priceChange": 0.02999999999999936,
    "priceChangePercent": 0.23474178403755366,
    "priceLast": 12.81,
    "sector": "Financials",
    "industryGroup": "Insurance",
    "securityType": 1,
    "volume": 2579908,
    "statusCode": "XD",
    "isin": "AU000000SUN6",
    "priceClose": 12.780000000000001,
    "priceDayHigh": 12.81,
    "priceDayLow": 12.61,
    "priceFiftyTwoWeekHigh": 13.12,
    "priceFiftyTwoWeekLow": 9.85,
    "volumeAverage": 3419221.10989,
    "dateExDate": "2023-02-14",
    "datePayDate": "2023-03-31",
    "dateRecordDate": "2023-02-15",
    "dividend": 0.33,
    "dividendType": "I",
    "frankingPercent": 100,
    "cashFlow": 1477,
    "earningsPerShare": 0.65471,
    "freeCashFlowYield": 0.06641954169187843,
    "priceEarningsRatio": 19.52009,
    "priceToCash": 15.05581,
    "foreignExempt": false,
    "shareDescription": "Ordinary Fully Paid",
    "numOfShares": 1264075597,
    "yieldAnnual": 6.479313036690086,
    "incomeStatement": [
      {
        "revenue": 16169000000,
        "netIncome": 681000000,
        "period": "2022A",
        "fPeriodEndDate": 44742,
        "curCode": "AUD"
      },
      {
        "revenue": 14187000000,
        "netIncome": 1033000000,
        "period": "2021A",
        "fPeriodEndDate": 44377,
        "curCode": "AUD"
      },
      {
        "revenue": 14772000000,
        "netIncome": 913000000,
        "period": "2020A",
        "fPeriodEndDate": 44012,
        "curCode": "AUD"
      },
      {
        "revenue": 15560000000,
        "netIncome": 175000000,
        "period": "2019A",
        "fPeriodEndDate": 43646,
        "curCode": "AUD"
      }
    ]
  },
  {
    "symbol": "TWR",
    "displayName": "TOWER LIMITED",
    "industry": "Insurance",
    "dateListed": "1999-09-28",
    "marketCap": 208716193,
    "xid": "56664148",
    "priceChangeFiveDayPercent": -7.4999999999999885,
    "isRecentListing": false,
    "priceAsk": 0.55,
    "priceBid": 0.54,
    "priceChange": 0.0050000000000000044,
    "priceChangePercent": 0.9090909090909098,
    "priceLast": 0.555,
    "sector": "Financials",
    "industryGroup": "Insurance",
    "securityType": 1,
    "volume": 17610,
    "statusCode": "RE",
    "isin": "NZTWRE0011S2",
    "priceClose": 0.55,
    "priceDayHigh": 0.5650000000000001,
    "priceDayLow": 0.54,
    "priceFiftyTwoWeekHigh": 0.75556,
    "priceFiftyTwoWeekLow": 0.505,
    "volumeAverage": 73287.371795,
    "dateExDate": "2023-01-17",
    "datePayDate": "2023-02-01",
    "dateRecordDate": "2023-01-18",
    "dividend": 0.0311,
    "dividendType": "F",
    "frankingPercent": 0,
    "cashFlow": 16.355,
    "earningsPerShare": 0.04577,
    "freeCashFlowYield": 0.16421412865520124,
    "priceEarningsRatio": 13.10902,
    "priceToCash": 6.08961,
    "foreignExempt": true,
    "shareDescription": "Ordinary Fully Paid Foreign Exempt Nzx",
    "numOfShares": 379483987,
    "yieldAnnual": 9.063063063063062,
    "incomeStatement": [
      {
        "revenue": 353214000,
        "netIncome": 18803000,
        "period": "2022A",
        "fPeriodEndDate": 44834,
        "curCode": "NZD"
      },
      {
        "revenue": 328040000,
        "netIncome": 18683000,
        "period": "2021A",
        "fPeriodEndDate": 44469,
        "curCode": "NZD"
      },
      {
        "revenue": 320676000,
        "netIncome": 10761000,
        "period": "2020A",
        "fPeriodEndDate": 44104,
        "curCode": "NZD"
      },
      {
        "revenue": 303357000,
        "netIncome": 16565000,
        "period": "2019A",
        "fPeriodEndDate": 43738,
        "curCode": "NZD"
      }
    ]
  }
]