[
  {
    "symbol": "AUB",
    "displayName": "AUB GROUP LIMITED",
    "industry": "Insurance",
    "dateListed": "2005-11-16",
    "marketCap": 1989998153,
    "xid": "3582563",
    "priceChangeFiveDayPercent": 1.1681056373793826,
    "isRecentListing": false,
    "priceAsk": 20.080000000000002,
    "priceBid": 19.62,
    "priceChange": 0.3200000000000003,
    "priceChangePercent": 1.6326530612244912,
    "priceLast": 19.92,
    "sector": "Financials",
    "industryGroup": "Insurance",
    "securityType": 1,
    "volume": 346913,
    "statusCode": ""
  },
  {
    "symbol": "ENA",
    "displayName": "ENSURANCE LTD",
    "industry": "Insurance",
    "dateListed": "2011-09-23",
    "marketCap": 20725286,
    "xid": "36099305",
    "priceChangeFiveDayPercent": 0,
    "isRecentListing": false,
    "priceAsk": 0.24,
    "priceBid": 0.21,
    "priceChange": 0,
    "priceChangePercent": 0,
    "priceLast": 0.23,
    "sector": "Financials",
    "industryGroup": "Insurance",
    "securityType": 1,
    "volume": 0,
    "statusCode": "",
    "isin": "AU000000ENA8",
    "priceClose": 0.23,
    "priceFiftyTwoWeekHigh": 0.3,
    "priceFiftyTwoWeekLow": 0.2,
    "volumeAverage": 71494.857143,
    "cashFlow": 0.44354,
    "earningsPerShare": 0.00327,
    "freeCashFlowYield": 0.017531243305256464,
    "priceEarningsRatio": 70.33639,
    "priceToCash": 57.04102,
    "foreignExempt": false,
    "shareDescription": "Ordinary Fully Paid",
    "numOfShares": 90109937,
    "yieldAnnual": 0,
    "incomeStatement": [
      {
        "revenue": 7314440,
        "netIncome": 273750,
        "period": "2022A",
        "fPeriodEndDate": 44742,
        "curCode": "AUD"
      },
      {
        "revenue": 4359120,
        "netIncome": -1302840,
        "period": "2021A",
        "fPeriodEndDate": 44377,
        "curCode": "AUD"
      },
      {
        "revenue": 3711330,
        "netIncome": -2153770,
        "period": "2020A",
        "fPeriodEndDate": 44012,
        "curCode": "AUD"
      },
      {
        "revenue": 1397390,
        "netIncome": -1401740,
        "period": "2019A",
        "fPeriodEndDate": 43646,
        "curCode": "AUD"
      }
    ]
  },
  {
    "symbol": "GDG",
    "displayName": "GENERATION DEVELOPMENT GROUP LIMITED",
    "industry": "Insurance",
    "dateListed": "2007-12-11",
    "marketCap": 212358907,
    "xid": "9390150",
    "priceChangeFiveDayPercent": -6.6666666666666545,
    "isRecentListing": false,
    "priceAsk": 1.16,
    "priceBid": 1.12,
    "priceChange": -0.004999999999999893,
    "priceChangePercent": -0.444444444444435,
    "priceLast": 1.12,
    "sector": "Financials",
    "industryGroup": "Insurance",
    "securityType": 1,
    "volume": 6582,
    "statusCode": "",
    "isin": "AU0000005126",
    "priceClose": 1.125,
    "priceDayHigh": 1.125,
    "priceDayLow": 1.12,
    "priceFiftyTwoWeekHigh": 1.79,
    "priceFiftyTwoWeekLow": 1.1,
    "volumeAverage": 130301.121622,
    "dateExDate": "2022-09-09",
    "datePayDate": "2022-10-06",
    "dateRecordDate": "2022-09-12",
    "dividend": 0.01,
    "dividendType": "F",
    "frankingPercent": 100,
    "cashFlow": -0.223,
    "earningsPerShare": 0.01057,
    "freeCashFlowYield": -0.0000100000010000001,
    "priceEarningsRatio": 108.7985,
    "priceToCash": -99999.99,
    "foreignExempt": false,
    "shareDescription": "Ordinary Fully Paid",
    "numOfShares": 188763473,
    "yieldAnnual": 1.7857142857142856,
    "incomeStatement": [
      {
        "revenue": -176093000,
        "netIncome": 1901000,
        "period": "2022A",
        "fPeriodEndDate": 44742,
        "curCode": "AUD"
      },
      {
        "revenue": 267445000,
        "netIncome": 2533000,
        "period": "2021A",
        "fPeriodEndDate": 44377,
        "curCode": "AUD"
      },
      {
        "revenue": -28148000,
        "netIncome": -1637000,
        "period": "2020A",
        "fPeriodEndDate": 44012,
        "curCode": "AUD"
      },
      {
        "revenue": 82225000,
        "netIncome": 5286000,
        "period": "2019A",
        "fPeriodEndDate": 43646,
        "curCode": "AUD"
      }
    ]
  },
  {
    "symbol": "IAG",
    "displayName": "INSURANCE AUSTRALIA GROUP LIMITED",
    "industry": "Insurance",
    "dateListed": "2000-08-08",
    "marketCap": 12054340007,
    "xid": "151417",
    "priceChangeFiveDayPercent": 3.821656050955408,
    "isRecentListing": false,
    "priceAsk": 4.92,
    "priceBid": 4.8500000000000005,
    "priceChange": 0,
    "priceChangePercent": 0,
    "priceLast": 4.89,
    "sector": "Financials",
    "industryGroup": "Insurance",
    "securityType": 1,
    "volume": 6393844,
    "statusCode": "",
    "isin": "AU000000IAG3",
    "priceClose": 4.89,
    "priceDayHigh": 4.94,
    "priceDayLow": 4.87,
    "priceFiftyTwoWeekHigh": 5.12,
    "priceFiftyTwoWeekLow": 4.02,
    "volumeAverage": 6811881.347826,
    "dateExDate": "2022-08-18",
    "datePayDate": "2022-09-22",
    "dateRecordDate": "2022-08-19",
    "dividend": 0.05,
    "dividendType": "F",
    "frankingPercent": 70,
    "cashFlow": 431,
    "earningsPerShare": 0.13333,
    "freeCashFlowYield": 0.04748196041618888,
    "priceEarningsRatio": 36.0759,
    "priceToCash": 21.06063,
    "foreignExempt": false,
    "shareDescription": "Ordinary Fully Paid",
    "numOfShares": 2465100206,
    "yieldAnnual": 2.2494887525562373,
    "incomeStatement": [
      {
        "revenue": 13913000000,
        "netIncome": 347000000,
        "period": "2022A",
        "fPeriodEndDate": 44742,
        "curCode": "AUD"
      },
      {
        "revenue": 13587000000,
        "netIncome": -427000000,
        "period": "2021A",
        "fPeriodEndDate": 44377,
        "curCode": "AUD"
      },
      {
        "revenue": 13417000000,
        "netIncome": 435000000,
        "period": "2020A",
        "fPeriodEndDate": 44012,
        "curCode": "AUD"
      },
      {
        "revenue": 13433000000,
        "netIncome": 1076000000,
        "period": "2019A",
        "fPeriodEndDate": 43646,
        "curCode": "AUD"
      }
    ]
  },
  {
    "symbol": "MPL",
    "displayName": "MEDIBANK PRIVATE LIMITED",
    "industry": "Insurance",
    "dateListed": "2014-11-25",
    "marketCap": 9639011340,
    "xid": "80536726",
    "priceChangeFiveDayPercent": -0.42613636363636714,
    "isRecentListing": false,
    "priceAsk": 3.5,
    "priceBid": 3.5100000000000002,
    "priceChange": 0.004999999999999893,
    "priceChangePercent": 0.14285714285713982,
    "priceLast": 3.505,
    "sector": "Financials",
    "industryGroup": "Insurance",
    "securityType": 1,
    "volume": 857749,
    "statusCode": "",
    "isin": "AU000000MPL3",
    "priceClose": 3.5,
    "priceDayHigh": 3.52,
    "priceDayLow": 3.49,
    "priceFiftyTwoWeekHigh": 3.785,
    "priceFiftyTwoWeekLow": 3,
    "volumeAverage": 8112542.944444,
    "dateExDate": "2022-09-07",
    "datePayDate": "2022-09-29",
    "dateRecordDate": "2022-09-08",
    "dividend": 0.073,
    "dividendType": "F",
    "frankingPercent": 100,
    "cashFlow": 555.4,
    "earningsPerShare": 0.14304,
    "freeCashFlowYield": 0.05249589088414105,
    "priceEarningsRatio": 24.6085,
    "priceToCash": 19.04911,
    "foreignExempt": false,
    "shareDescription": "Ordinary Fully Paid",
    "numOfShares": 2754003240,
    "yieldAnnual": 3.823109843081312,
    "incomeStatement": [
      {
        "revenue": 7108800000,
        "netIncome": 393900000,
        "period": "2022A",
        "fPeriodEndDate": 44742,
        "curCode": "AUD"
      },
      {
        "revenue": 7035100000,
        "netIncome": 441200000,
        "period": "2021A",
        "fPeriodEndDate": 44377,
        "curCode": "AUD"
      },
      {
        "revenue": 6776600000,
        "netIncome": 315000000,
        "period": "2020A",
        "fPeriodEndDate": 44012,
        "curCode": "AUD"
      },
      {
        "revenue": 6763200000,
        "netIncome": 458700000,
        "period": "2019A",
        "fPeriodEndDate": 43646,
        "curCode": "AUD"
      }
    ]
  },
  {
    "symbol": "NHF",
    "displayName": "NIB HOLDINGS LIMITED",
    "industry": "Insurance",
    "dateListed": "2007-11-05",
    "marketCap": 3230159080,
    "xid": "9141105",
    "priceChangeFiveDayPercent": -8.788282290279618,
    "isRecentListing": false,
    "priceAsk": 6.9,
    "priceBid": 6.82,
    "priceChange": 0.11000000000000032,
    "priceChangePercent": 1.6320474777448117,
    "priceLast": 6.8500000000000005,
    "sector": "Financials",
    "industryGroup": "Insurance",
    "securityType": 1,
    "volume": 1339790,
    "statusCode": "",
    "isin": "AU000000NHF0",
    "priceClose": 6.74,
    "priceDayHigh": 6.890000000000001,
    "priceDayLow": 6.8,
    "priceFiftyTwoWeekHigh": 8.195,
    "priceFiftyTwoWeekLow": 6.07,
    "volumeAverage": 968627.747253,
    "dateExDate": "2022-09-05",
    "datePayDate": "2022-10-04",
    "dateRecordDate": "2022-09-06",
    "dividend": 0.11,
    "dividendType": "F",
    "frankingPercent": 100,
    "cashFlow": 196.7,
    "earningsPerShare": 0.29607,
    "freeCashFlowYield": 0.05210241041381298,
    "priceEarningsRatio": 23.33908,
    "priceToCash": 19.19297,
    "foreignExempt": false,
    "shareDescription": "Ordinary Fully Paid",
    "numOfShares": 479252089,
    "yieldAnnual": 3.2116788321167884,
    "incomeStatement": [
      {
        "revenue": 2715500000,
        "netIncome": 133800000,
        "period": "2022A",
        "fPeriodEndDate": 44742,
        "curCode": "AUD"
      },
      {
        "revenue": 2611400000,
        "netIncome": 160500000,
        "period": "2021A",
        "fPeriodEndDate": 44377,
        "curCode": "AUD"
      },
      {
        "revenue": 2509700000,
        "netIncome": 87000000,
        "period": "2020A",
        "fPeriodEndDate": 44012,
        "curCode": "AUD"
      },
      {
        "revenue": 2451500000,
        "netIncome": 149300000,
        "period": "2019A",
        "fPeriodEndDate": 43646,
        "curCode": "AUD"
      }
    ]
  },
  {
    "symbol": "NOL",
    "displayName": "NOBLEOAK LIFE LIMITED",
    "industry": "Insurance",
    "dateListed": "2021-07-22",
    "marketCap": 146131459,
    "xid": "667331428",
    "priceChangeFiveDayPercent": -4.249291784702547,
    "isRecentListing": false,
    "priceAsk": 1.93,
    "priceBid": 1.6500000000000001,
    "priceChange": -0.010000000000000009,
    "priceChangePercent": -0.5882352941176476,
    "priceLast": 1.69,
    "sector": "Financials",
    "industryGroup": "Insurance",
    "securityType": 1,
    "volume": 12259,
    "statusCode": "",
    "isin": "AU0000161580",
    "priceClose": 1.7,
    "priceDayHigh": 1.715,
    "priceDayLow": 1.69,
    "priceFiftyTwoWeekHigh": 2.45,
    "priceFiftyTwoWeekLow": 1.655,
    "volumeAverage": 12963.362069,
    "cashFlow": 15.332,
    "earningsPerShare": 0.02245,
    "freeCashFlowYield": 0.022281927885877312,
    "priceEarningsRatio": 77.50557,
    "priceToCash": 44.87942,
    "foreignExempt": false,
    "shareDescription": "Ordinary Fully Paid",
    "numOfShares": 85959682,
    "yieldAnnual": 0,
    "incomeStatement": [
      {
        "revenue": 83401000,
        "netIncome": 1685000,
        "period": "2022A",
        "fPeriodEndDate": 44742,
        "curCode": "AUD"
      },
      {
        "revenue": 63494000,
        "netIncome": 4903000,
        "period": "2021A",
        "fPeriodEndDate": 44377,
        "curCode": "AUD"
      },
      {
        "revenue": 106556000,
        "netIncome": 7636000,
        "period": "2020A",
        "fPeriodEndDate": 44012,
        "curCode": "AUD"
      },
      {
        "revenue": 30253500,
        "netIncome": 5233390,
        "period": "2019A",
        "fPeriodEndDate": 43646,
        "curCode": "AUD"
      }
    ]
  },
  {
    "symbol": "PSI",
    "displayName": "PSC INSURANCE GROUP LIMITED",
    "industry": "Insurance",
    "dateListed": "2015-12-15",
    "marketCap": 1670569714,
    "xid": "320554376",
    "priceChangeFiveDayPercent": -3.0927835051546286,
    "isRecentListing": false,
    "priceAsk": 4.76,
    "priceBid": 4.61,
    "priceChange": -0.040000000000000036,
    "priceChangePercent": -0.8438818565400851,
    "priceLast": 4.7,
    "sector": "Financials",
    "industryGroup": "Insurance",
    "securityType": 1,
    "volume": 21663,
    "statusCode": "",
    "isin": "AU000000PSI6",
    "priceClose": 4.74,
    "priceDayHigh": 4.8,
    "priceDayLow": 4.7,
    "priceFiftyTwoWeekHigh": 5.3,
    "priceFiftyTwoWeekLow": 3.9,
    "volumeAverage": 149149.706522,
    "dateExDate": "2022-09-13",
    "datePayDate": "2022-10-12",
    "dateRecordDate": "2022-09-14",
    "dividend": 0.075,
    "dividendType": "F",
    "frankingPercent": 60,
    "cashFlow": 31.937,
    "earningsPerShare": 0.0789,
    "freeCashFlowYield": 0.028217428833528176,
    "priceEarningsRatio": 60.8365,
    "priceToCash": 35.43909,
    "foreignExempt": false,
    "shareDescription": "Ordinary Fully Paid",
    "numOfShares": 352440868,
    "yieldAnnual": 2.553191489361702,
    "incomeStatement": [
      {
        "revenue": 252768000,
        "netIncome": 26658000,
        "period": "2022A",
        "fPeriodEndDate": 44742,
        "curCode": "AUD"
      },
      {
        "revenue": 205840000,
        "netIncome": 40447000,
        "period": "2021A",
        "fPeriodEndDate": 44377,
        "curCode": "AUD"
      },
      {
        "revenue": 175669000,
        "netIncome": 17887000,
        "period": "2020A",
        "fPeriodEndDate": 44012,
        "curCode": "AUD"
      },
      {
        "revenue": 117238000,
        "netIncome": 24693000,
        "period": "2019A",
        "fPeriodEndDate": 43646,
        "curCode": "AUD"
      }
    ]
  },
  {
    "symbol": "QBE",
    "displayName": "QBE INSURANCE GROUP LIMITED",
    "industry": "Insurance",
    "dateListed": "1973-06-28",
    "marketCap": 17742252594,
    "xid": "237176",
    "priceChangeFiveDayPercent": 2.9991431019708625,
    "isRecentListing": false,
    "priceAsk": 12.040000000000001,
    "priceBid": 12,
    "priceChange": 0.06999999999999851,
    "priceChangePercent": 0.5857740585773933,
    "priceLast": 12.02,
    "sector": "Financials",
    "industryGroup": "Insurance",
    "securityType": 1,
    "volume": 2705028,
    "statusCode": "",
    "isin": "AU000000QBE9",
    "priceClose": 11.950000000000001,
    "priceDayHigh": 12.05,
    "priceDayLow": 11.86,
    "priceFiftyTwoWeekHigh": 12.88,
    "priceFiftyTwoWeekLow": 10,
    "volumeAverage": 3725415.858696,
    "dateExDate": "2022-08-18",
    "datePayDate": "2022-09-23",
    "dateRecordDate": "2022-08-19",
    "dividend": 0.09,
    "dividendType": "I",
    "frankingPercent": 10,
    "cashFlow": 2966.029,
    "earningsPerShare": 0.43822,
    "freeCashFlowYield": 0.04783199108794342,
    "priceEarningsRatio": 27.90838,
    "priceToCash": 20.90651,
    "foreignExempt": false,
    "shareDescription": "Ordinary Fully Paid",
    "numOfShares": 1484707330,
    "yieldAnnual": 2.3294509151414307,
    "incomeStatement": [
      {
        "revenue": 17261000000,
        "netIncome": 750000000,
        "period": "2021A",
        "fPeriodEndDate": 44561,
        "curCode": "USD"
      },
      {
        "revenue": 15747000000,
        "netIncome": -1517000000,
        "period": "2020A",
        "fPeriodEndDate": 44196,
        "curCode": "USD"
      },
      {
        "revenue": 14594000000,
        "netIncome": 550000000,
        "period": "2019A",
        "fPeriodEndDate": 43830,
        "curCode": "USD"
      },
      {
        "revenue": 13976000000,
        "netIncome": 390000000,
        "period": "2018A",
        "fPeriodEndDate": 43465,
        "curCode": "USD"
      }
    ]
  },
  {
    "symbol": "SDF",
    "displayName": "STEADFAST GROUP LIMITED",
    "industry": "Insurance",
    "dateListed": "2013-08-02",
    "marketCap": 4835359516,
    "xid": "59611073",
    "priceChangeFiveDayPercent": 0,
    "isRecentListing": false,
    "priceAsk": 4.79,
    "priceBid": 4.65,
    "priceChange": 0.04999999999999982,
    "priceChangePercent": 1.0706638115631655,
    "priceLast": 4.72,
    "sector": "Financials",
    "industryGroup": "Insurance",
    "securityType": 1,
    "volume": 1897774,
    "statusCode": "",
    "isin": "AU000000SDF8",
    "priceClose": 4.67,
    "priceDayHigh": 4.74,
    "priceDayLow": 4.66,
    "priceFiftyTwoWeekHigh": 5.5,
    "priceFiftyTwoWeekLow": 4.27,
    "volumeAverage": 2717166.175824,
    "dateExDate": "2022-08-22",
    "datePayDate": "2022-09-09",
    "dateRecordDate": "2022-08-23",
    "dividend": 0.078,
    "dividendType": "F",
    "frankingPercent": 100,
    "cashFlow": 131.3,
    "earningsPerShare": 0.18131,
    "freeCashFlowYield": 0.05684550641956305,
    "priceEarningsRatio": 26.08792,
    "priceToCash": 17.59154,
    "foreignExempt": false,
    "shareDescription": "Ordinary Fully Paid",
    "numOfShares": 1035408890,
    "yieldAnnual": 2.754237288135593,
    "incomeStatement": [
      {
        "revenue": 1129000000,
        "netIncome": 171600000,
        "period": "2022A",
        "fPeriodEndDate": 44742,
        "curCode": "AUD"
      },
      {
        "revenue": 902000000,
        "netIncome": 143000000,
        "period": "2021A",
        "fPeriodEndDate": 44377,
        "curCode": "AUD"
      },
      {
        "revenue": 814195000,
        "netIncome": -55244000,
        "period": "2020A",
        "fPeriodEndDate": 44012,
        "curCode": "AUD"
      },
      {
        "revenue": 681734000,
        "netIncome": 103845000,
        "period": "2019A",
        "fPeriodEndDate": 43646,
        "curCode": "AUD"
      }
    ]
  },
  {
    "symbol": "SUN",
    "displayName": "SUNCORP GROUP LIMITED",
    "industry": "Insurance",
    "dateListed": "1988-07-07",
    "marketCap": 13424482840,
    "xid": "262335",
    "priceChangeFiveDayPercent": 3.003875968992253,
    "isRecentListing": false,
    "priceAsk": 10.65,
    "priceBid": 10.5,
    "priceChange": 0.009999999999999787,
    "priceChangePercent": 0.09416195856873621,
    "priceLast": 10.63,
    "sector": "Financials",
    "industryGroup": "Insurance",
    "securityType": 1,
    "volume": 2234587,
    "statusCode": "",
    "isin": "AU000000SUN6",
    "priceClose": 10.620000000000001,
    "priceDayHigh": 10.66,
    "priceDayLow": 10.450000000000001,
    "priceFiftyTwoWeekHigh": 12.54,
    "priceFiftyTwoWeekLow": 9.85,
    "volumeAverage": 3483817.815217,
    "dateExDate": "2022-08-12",
    "datePayDate": "2022-09-21",
    "dateRecordDate": "2022-08-15",
    "dividend": 0.17,
    "dividendType": "F",
    "frankingPercent": 100,
    "cashFlow": 1580,
    "earningsPerShare": 0.51571,
    "freeCashFlowYield": 0.06654869800799783,
    "priceEarningsRatio": 20.88383,
    "priceToCash": 15.02659,
    "foreignExempt": false,
    "shareDescription": "Ordinary Fully Paid",
    "numOfShares": 1264075597,
    "yieldAnnual": 3.762935089369708,
    "incomeStatement": [
      {
        "revenue": 16169000000,
        "netIncome": 681000000,
        "period": "2022A",
        "fPeriodEndDate": 44742,
        "curCode": "AUD"
      },
      {
        "revenue": 14187000000,
        "netIncome": 1033000000,
        "period": "2021A",
        "fPeriodEndDate": 44377,
        "curCode": "AUD"
      },
      {
        "revenue": 14772000000,
        "netIncome": 913000000,
        "period": "2020A",
        "fPeriodEndDate": 44012,
        "curCode": "AUD"
      },
      {
        "revenue": 15560000000,
        "netIncome": 175000000,
        "period": "2019A",
        "fPeriodEndDate": 43646,
        "curCode": "AUD"
      }
    ]
  },
  {
    "symbol": "TWR",
    "displayName": "TOWER LIMITED",
    "industry": "Insurance",
    "dateListed": "1999-09-28",
    "marketCap": 220100712,
    "xid": "56664148",
    "priceChangeFiveDayPercent": 0,
    "isRecentListing": false,
    "priceAsk": 0.61,
    "priceBid": 0.56,
    "priceChange": -0.02499999999999991,
    "priceChangePercent": -4.310344827586192,
    "priceLast": 0.555,
    "sector": "Financials",
    "industryGroup": "Insurance",
    "securityType": 1,
    "volume": 355,
    "statusCode": "RE",
    "isin": "NZTWRE0011S2",
    "priceClose": 0.58,
    "priceDayHigh": 0.555,
    "priceDayLow": 0.555,
    "priceFiftyTwoWeekHigh": 0.78889,
    "priceFiftyTwoWeekLow": 0.505,
    "volumeAverage": 16033.382353,
    "dateExDate": "2022-06-15",
    "datePayDate": "2022-06-30",
    "dateRecordDate": "2022-06-16",
    "dividend": 0.0192,
    "dividendType": "I",
    "frankingPercent": 0,
    "cashFlow": 27.938,
    "earningsPerShare": 0.02597,
    "freeCashFlowYield": 0.12097735182996393,
    "priceEarningsRatio": 23.68117,
    "priceToCash": 8.26601,
    "foreignExempt": true,
    "shareDescription": "Ordinary Fully Paid Foreign Exempt Nzx",
    "numOfShares": 379483987,
    "yieldAnnual": 6.9909909909909915,
    "incomeStatement": [
      {
        "revenue": 333499000,
        "netIncome": 18683000,
        "period": "2021A",
        "fPeriodEndDate": 44469,
        "curCode": "NZD"
      },
      {
        "revenue": 320676000,
        "netIncome": 10761000,
        "period": "2020A",
        "fPeriodEndDate": 44104,
        "curCode": "NZD"
      },
      {
        "revenue": 303357000,
        "netIncome": 16565000,
        "period": "2019A",
        "fPeriodEndDate": 43738,
        "curCode": "NZD"
      },
      {
        "revenue": 281722000,
        "netIncome": -6773000,
        "period": "2018A",
        "fPeriodEndDate": 43373,
        "curCode": "NZD"
      }
    ]
  }
]