[
  {
    "symbol": "3PL",
    "displayName": "3P LEARNING LIMITED..",
    "industry": "Consumer Services",
    "dateListed": "2014-07-09",
    "marketCap": 359429421,
    "xid": "76419072",
    "priceChangeFiveDayPercent": 1.5625000000000013,
    "isRecentListing": false,
    "priceAsk": 1.3,
    "priceBid": 1.26,
    "priceChange": 0,
    "priceChangePercent": 0,
    "priceLast": 1.3,
    "sector": "Consumer Discretionary",
    "industryGroup": "Consumer Services",
    "securityType": 1,
    "volume": 0,
    "statusCode": "",
    "isin": "AU0000003PL9",
    "priceClose": 1.3,
    "priceFiftyTwoWeekHigh": 1.85,
    "priceFiftyTwoWeekLow": 1.165,
    "volumeAverage": 9233.722222,
    "dateExDate": "2015-10-06",
    "datePayDate": "2015-10-22",
    "dateRecordDate": "2015-10-08",
    "dividend": 0.018,
    "dividendType": "F",
    "frankingPercent": 100,
    "cashFlow": 7.651,
    "earningsPerShare": -0.00194,
    "freeCashFlowYield": 0.03164459825125621,
    "priceEarningsRatio": -99999.99,
    "priceToCash": 31.60097,
    "foreignExempt": false,
    "shareDescription": "Ordinary Fully Paid",
    "numOfShares": 276484170,
    "yieldAnnual": 0,
    "incomeStatement": [
      {
        "revenue": 97288000,
        "netIncome": -536000,
        "period": "2022A",
        "fPeriodEndDate": 44742,
        "curCode": "AUD"
      },
      {
        "revenue": 57563000,
        "netIncome": -9369000,
        "period": "2021A",
        "fPeriodEndDate": 44377,
        "curCode": "AUD"
      },
      {
        "revenue": 55225000,
        "netIncome": 517000,
        "period": "2020A",
        "fPeriodEndDate": 44012,
        "curCode": "AUD"
      },
      {
        "revenue": 54682000,
        "netIncome": 5911000,
        "period": "2019A",
        "fPeriodEndDate": 43646,
        "curCode": "AUD"
      }
    ]
  },
  {
    "symbol": "8VI",
    "displayName": "8VI HOLDINGS LIMITED",
    "industry": "Consumer Services",
    "dateListed": "2015-12-16",
    "marketCap": 29878903,
    "xid": "320037656",
    "priceChangeFiveDayPercent": 4.41176470588234,
    "isRecentListing": false,
    "priceAsk": 0.8,
    "priceBid": 0.71,
    "priceChange": 0.0050000000000000044,
    "priceChangePercent": 0.7092198581560291,
    "priceLast": 0.71,
    "sector": "Consumer Discretionary",
    "industryGroup": "Consumer Services",
    "securityType": 1,
    "volume": 1695,
    "statusCode": "",
    "isin": "AU0000026007",
    "priceClose": 0.705,
    "priceDayHigh": 0.71,
    "priceDayLow": 0.705,
    "priceFiftyTwoWeekHigh": 4.1,
    "priceFiftyTwoWeekLow": 0.67,
    "volumeAverage": 11317.112903,
    "cashFlow": -1.07295,
    "earningsPerShare": -0.13603,
    "freeCashFlowYield": -0.0000100000010000001,
    "priceEarningsRatio": -99999.99,
    "priceToCash": -99999.99,
    "foreignExempt": false,
    "shareDescription": "Chess Depositary Interests 1:1",
    "numOfShares": 42381422,
    "yieldAnnual": 0,
    "incomeStatement": [
      {
        "revenue": 31353140,
        "netIncome": 1985400,
        "period": "2022A",
        "fPeriodEndDate": 44651,
        "curCode": "SGD"
      },
      {
        "revenue": 25960660,
        "netIncome": 5861410,
        "period": "2021A",
        "fPeriodEndDate": 44286,
        "curCode": "SGD"
      },
      {
        "revenue": 10859350,
        "netIncome": 1072050,
        "period": "2020A",
        "fPeriodEndDate": 43921,
        "curCode": "SGD"
      },
      {
        "revenue": 22291340,
        "netIncome": -4867350,
        "period": "2019A",
        "fPeriodEndDate": 43555,
        "curCode": "SGD"
      }
    ]
  },
  {
    "symbol": "AKG",
    "displayName": "ACADEMIES AUSTRALASIA GROUP LIMITED",
    "industry": "Consumer Services",
    "dateListed": "1977-06-01",
    "marketCap": 52045787,
    "xid": "142001",
    "priceChangeFiveDayPercent": 3.8961038961038996,
    "isRecentListing": false,
    "priceAsk": 0.41000000000000003,
    "priceBid": 0.4,
    "priceChange": 0,
    "priceChangePercent": 0,
    "priceLast": 0.4,
    "sector": "Consumer Discretionary",
    "industryGroup": "Consumer Services",
    "securityType": 1,
    "volume": 41297,
    "statusCode": "",
    "isin": "AU000000AKG9",
    "priceClose": 0.4,
    "priceDayHigh": 0.4,
    "priceDayLow": 0.39,
    "priceFiftyTwoWeekHigh": 0.455,
    "priceFiftyTwoWeekLow": 0.22,
    "volumeAverage": 104971.790323,
    "dateExDate": "2021-03-04",
    "datePayDate": "2021-03-26",
    "dateRecordDate": "2021-03-05",
    "dividend": 0.005,
    "dividendType": "I",
    "frankingPercent": 100,
    "cashFlow": 8.691,
    "earningsPerShare": -0.00955,
    "freeCashFlowYield": 0.0923033753498298,
    "priceEarningsRatio": -99999.99,
    "priceToCash": 10.83384,
    "foreignExempt": false,
    "shareDescription": "Ordinary Fully Paid",
    "numOfShares": 130114467,
    "yieldAnnual": 0,
    "incomeStatement": [
      {
        "revenue": 36042000,
        "netIncome": -1302000,
        "period": "2022A",
        "fPeriodEndDate": 44742,
        "curCode": "AUD"
      },
      {
        "revenue": 42624000,
        "netIncome": -1241000,
        "period": "2021A",
        "fPeriodEndDate": 44377,
        "curCode": "AUD"
      },
      {
        "revenue": 59694000,
        "netIncome": 3604000,
        "period": "2020A",
        "fPeriodEndDate": 44012,
        "curCode": "AUD"
      },
      {
        "revenue": 66056000,
        "netIncome": 4350000,
        "period": "2019A",
        "fPeriodEndDate": 43646,
        "curCode": "AUD"
      }
    ]
  },
  {
    "symbol": "AGI",
    "displayName": "AINSWORTH GAME TECHNOLOGY LIMITED",
    "industry": "Consumer Services",
    "dateListed": "2001-12-17",
    "marketCap": 340161868,
    "xid": "40562",
    "priceChangeFiveDayPercent": 8.499999999999996,
    "isRecentListing": false,
    "priceAsk": 1.085,
    "priceBid": 1.01,
    "priceChange": 0.07499999999999996,
    "priceChangePercent": 7.425742574257422,
    "priceLast": 1.085,
    "sector": "Consumer Discretionary",
    "industryGroup": "Consumer Services",
    "securityType": 1,
    "volume": 5672,
    "statusCode": "",
    "isin": "AU000000AGI3",
    "priceClose": 1.01,
    "priceDayHigh": 1.085,
    "priceDayLow": 1.025,
    "priceFiftyTwoWeekHigh": 1.35,
    "priceFiftyTwoWeekLow": 0.77,
    "volumeAverage": 47087.880952,
    "dateExDate": "2018-10-04",
    "datePayDate": "2018-11-07",
    "dateRecordDate": "2018-10-05",
    "dividend": 0.025,
    "dividendType": "F",
    "frankingPercent": 100,
    "cashFlow": 45.797,
    "earningsPerShare": 0.03688,
    "freeCashFlowYield": 0.09279967334514984,
    "priceEarningsRatio": 29.41974,
    "priceToCash": 10.7759,
    "foreignExempt": false,
    "shareDescription": "Ordinary Fully Paid",
    "numOfShares": 336793929,
    "yieldAnnual": 0,
    "incomeStatement": [
      {
        "revenue": 220157000,
        "netIncome": 11753000,
        "period": "2022A",
        "fPeriodEndDate": 44742,
        "curCode": "AUD"
      },
      {
        "revenue": 159520000,
        "netIncome": -53409000,
        "period": "2021A",
        "fPeriodEndDate": 44377,
        "curCode": "AUD"
      },
      {
        "revenue": 149396000,
        "netIncome": -43433000,
        "period": "2020A",
        "fPeriodEndDate": 44012,
        "curCode": "AUD"
      },
      {
        "revenue": 234344000,
        "netIncome": 10895000,
        "period": "2019A",
        "fPeriodEndDate": 43646,
        "curCode": "AUD"
      }
    ]
  },
  {
    "symbol": "ALO",
    "displayName": "ALLOGGIO GROUP LIMITED",
    "industry": "Consumer Services",
    "dateListed": "2021-11-29",
    "marketCap": 44160605,
    "xid": "687332183",
    "priceChangeFiveDayPercent": -2.222222222222224,
    "isRecentListing": false,
    "priceAsk": 0.24,
    "priceBid": 0.23,
    "priceChange": 0,
    "priceChangePercent": 0,
    "priceLast": 0.22,
    "sector": "Consumer Discretionary",
    "industryGroup": "Consumer Services",
    "securityType": 1,
    "volume": 0,
    "statusCode": "",
    "isin": "AU0000183915",
    "priceClose": 0.22,
    "priceFiftyTwoWeekHigh": 0.265,
    "priceFiftyTwoWeekLow": 0.115,
    "volumeAverage": 226551.204819,
    "cashFlow": -9.64881,
    "earningsPerShare": 0.01002,
    "freeCashFlowYield": 0.29311158464916015,
    "priceEarningsRatio": 21.95609,
    "priceToCash": 3.41167,
    "foreignExempt": false,
    "shareDescription": "Ordinary Fully Paid",
    "numOfShares": 200730021,
    "yieldAnnual": 0,
    "incomeStatement": [
      {
        "revenue": 27834800,
        "netIncome": 2010680,
        "period": "2022A",
        "fPeriodEndDate": 44742,
        "curCode": "AUD"
      },
      {
        "revenue": 11293070,
        "netIncome": 98480,
        "period": "2021A",
        "fPeriodEndDate": 44377,
        "curCode": "AUD"
      },
      {
        "revenue": 7456110,
        "netIncome": -940730,
        "period": "2020A",
        "fPeriodEndDate": 44012,
        "curCode": "AUD"
      },
      {
        "revenue": 5780430,
        "netIncome": -918730,
        "period": "2019A",
        "fPeriodEndDate": 43646,
        "curCode": "AUD"
      }
    ]
  },
  {
    "symbol": "AQS",
    "displayName": "AQUIS ENTERTAINMENT LIMITED",
    "industry": "Consumer Services",
    "dateListed": "2011-12-02",
    "marketCap": 28696863,
    "xid": "38312852",
    "priceChangeFiveDayPercent": 0,
    "isRecentListing": false,
    "priceAsk": 0.16,
    "priceBid": 0.155,
    "priceChange": 0.0050000000000000044,
    "priceChangePercent": 3.225806451612906,
    "priceLast": 0.16,
    "sector": "Consumer Discretionary",
    "industryGroup": "Consumer Services",
    "securityType": 1,
    "volume": 7032,
    "statusCode": "",
    "isin": "AU000000AQS1",
    "priceClose": 0.155,
    "priceDayHigh": 0.16,
    "priceDayLow": 0.155,
    "priceFiftyTwoWeekHigh": 0.2,
    "priceFiftyTwoWeekLow": 0.1,
    "volumeAverage": 19371.1,
    "cashFlow": 5.4029,
    "earningsPerShare": 0.01636,
    "freeCashFlowYield": 0.8494877588813945,
    "priceEarningsRatio": 9.77995,
    "priceToCash": 1.17718,
    "foreignExempt": false,
    "shareDescription": "Ordinary Fully Paid",
    "numOfShares": 185141050,
    "yieldAnnual": 0,
    "incomeStatement": [
      {
        "revenue": 25184470,
        "netIncome": 230800,
        "period": "2021A",
        "fPeriodEndDate": 44561,
        "curCode": "AUD"
      },
      {
        "revenue": 18933180,
        "netIncome": 798200,
        "period": "2020A",
        "fPeriodEndDate": 44196,
        "curCode": "AUD"
      },
      {
        "revenue": 24801350,
        "netIncome": -3957190,
        "period": "2019A",
        "fPeriodEndDate": 43830,
        "curCode": "AUD"
      },
      {
        "revenue": 26411230,
        "netIncome": -3396830,
        "period": "2018A",
        "fPeriodEndDate": 43465,
        "curCode": "AUD"
      }
    ]
  },
  {
    "symbol": "ALG",
    "displayName": "ARDENT LEISURE GROUP LIMITED",
    "industry": "Consumer Services",
    "dateListed": "2018-11-30",
    "marketCap": 292620670,
    "xid": "504280917",
    "priceChangeFiveDayPercent": -0.8196721311475418,
    "isRecentListing": false,
    "priceAsk": 0.61,
    "priceBid": 0.6,
    "priceChange": -0.0050000000000000044,
    "priceChangePercent": -0.8196721311475418,
    "priceLast": 0.605,
    "sector": "Consumer Discretionary",
    "industryGroup": "Consumer Services",
    "securityType": 1,
    "volume": 50186,
    "statusCode": "",
    "isin": "AU0000027484",
    "priceClose": 0.61,
    "priceDayHigh": 0.61,
    "priceDayLow": 0.605,
    "priceFiftyTwoWeekHigh": 1.62,
    "priceFiftyTwoWeekLow": 0.465,
    "volumeAverage": 1493396.879121,
    "dateExDate": "2022-07-05",
    "datePayDate": "2022-07-13",
    "dateRecordDate": "2022-07-06",
    "dividend": 0.4893,
    "dividendType": "I",
    "frankingPercent": 0,
    "cashFlow": 50.6,
    "earningsPerShare": -0.12814,
    "freeCashFlowYield": 0.029725508707493267,
    "priceEarningsRatio": -99999.99,
    "priceToCash": 33.64114,
    "foreignExempt": false,
    "shareDescription": "Ordinary Fully Paid",
    "numOfShares": 479706016,
    "yieldAnnual": 0,
    "incomeStatement": [
      {
        "revenue": 49490000,
        "netIncome": -97431000,
        "period": "2022A",
        "fPeriodEndDate": 44740,
        "curCode": "AUD"
      },
      {
        "revenue": 36049000,
        "netIncome": -86932000,
        "period": "2021A",
        "fPeriodEndDate": 44376,
        "curCode": "AUD"
      },
      {
        "revenue": 398995000,
        "netIncome": -136095000,
        "period": "2020A",
        "fPeriodEndDate": 44012,
        "curCode": "AUD"
      },
      {
        "revenue": 483640000,
        "netIncome": -60877000,
        "period": "2019A",
        "fPeriodEndDate": 43641,
        "curCode": "AUD"
      }
    ]
  },
  {
    "symbol": "ALL",
    "displayName": "ARISTOCRAT LEISURE LIMITED",
    "industry": "Consumer Services",
    "dateListed": "1996-07-09",
    "marketCap": 20234833991,
    "xid": "43238",
    "priceChangeFiveDayPercent": -0.7479674796747982,
    "isRecentListing": false,
    "priceAsk": 30.71,
    "priceBid": 30.51,
    "priceChange": -0.26000000000000156,
    "priceChangePercent": -0.8447043534762884,
    "priceLast": 30.52,
    "sector": "Consumer Discretionary",
    "industryGroup": "Consumer Services",
    "securityType": 1,
    "volume": 1052219,
    "statusCode": "",
    "isin": "AU000000ALL7",
    "priceClose": 30.78,
    "priceDayHigh": 31.25,
    "priceDayLow": 30.52,
    "priceFiftyTwoWeekHigh": 45.84,
    "priceFiftyTwoWeekLow": 30.46,
    "volumeAverage": 1564610.274725,
    "dateExDate": "2022-11-30",
    "datePayDate": "2022-12-16",
    "dateRecordDate": "2022-12-01",
    "dividend": 0.26,
    "dividendType": "F",
    "frankingPercent": 100,
    "cashFlow": 629.4,
    "earningsPerShare": 1.42389,
    "freeCashFlowYield": 0.06573990925262928,
    "priceEarningsRatio": 21.43424,
    "priceToCash": 15.21146,
    "foreignExempt": false,
    "shareDescription": "Ordinary Fully Paid",
    "numOfShares": 657402014,
    "yieldAnnual": 1.7038007863695936,
    "incomeStatement": [
      {
        "revenue": 5573700000,
        "netIncome": 948500000,
        "period": "2022A",
        "fPeriodEndDate": 44834,
        "curCode": "AUD"
      },
      {
        "revenue": 4736600000,
        "netIncome": 820000000,
        "period": "2021A",
        "fPeriodEndDate": 44469,
        "curCode": "AUD"
      },
      {
        "revenue": 4139100000,
        "netIncome": 1377700000,
        "period": "2020A",
        "fPeriodEndDate": 44104,
        "curCode": "AUD"
      },
      {
        "revenue": 4397400000,
        "netIncome": 698800000,
        "period": "2019A",
        "fPeriodEndDate": 43738,
        "curCode": "AUD"
      }
    ]
  },
  {
    "symbol": "BET",
    "displayName": "BETMAKERS TECHNOLOGY GROUP LTD",
    "industry": "Consumer Services",
    "dateListed": "2015-12-11",
    "marketCap": 263774672,
    "xid": "320048269",
    "priceChangeFiveDayPercent": 0,
    "isRecentListing": false,
    "priceAsk": 0.275,
    "priceBid": 0.27,
    "priceChange": -0.0050000000000000044,
    "priceChangePercent": -1.7857142857142871,
    "priceLast": 0.275,
    "sector": "Consumer Discretionary",
    "industryGroup": "Consumer Services",
    "securityType": 1,
    "volume": 1237263,
    "statusCode": "",
    "isin": "AU0000050585",
    "priceClose": 0.28,
    "priceDayHigh": 0.28500000000000003,
    "priceDayLow": 0.27,
    "priceFiftyTwoWeekHigh": 0.84,
    "priceFiftyTwoWeekLow": 0.24,
    "volumeAverage": 3897383.087912,
    "cashFlow": -34.384,
    "earningsPerShare": -0.10119,
    "freeCashFlowYield": -0.0000100000010000001,
    "priceEarningsRatio": -99999.99,
    "priceToCash": -99999.99,
    "foreignExempt": false,
    "shareDescription": "Ordinary Fully Paid",
    "numOfShares": 942052401,
    "yieldAnnual": 0,
    "incomeStatement": [
      {
        "revenue": 91682000,
        "netIncome": -89234000,
        "period": "2022A",
        "fPeriodEndDate": 44742,
        "curCode": "AUD"
      },
      {
        "revenue": 19460510,
        "netIncome": -17459040,
        "period": "2021A",
        "fPeriodEndDate": 44377,
        "curCode": "AUD"
      },
      {
        "revenue": 8583160,
        "netIncome": -2140550,
        "period": "2020A",
        "fPeriodEndDate": 44012,
        "curCode": "AUD"
      },
      {
        "revenue": 6169130,
        "netIncome": -3604760,
        "period": "2019A",
        "fPeriodEndDate": 43646,
        "curCode": "AUD"
      }
    ]
  },
  {
    "symbol": "BBT",
    "displayName": "BLUEBET HOLDINGS LTD",
    "industry": "Consumer Services",
    "dateListed": "2021-07-02",
    "marketCap": 72072442,
    "xid": "663337257",
    "priceChangeFiveDayPercent": 0,
    "isRecentListing": false,
    "priceAsk": 0.38,
    "priceBid": 0.365,
    "priceChange": 0.0050000000000000044,
    "priceChangePercent": 1.3888888888888902,
    "priceLast": 0.365,
    "sector": "Consumer Discretionary",
    "industryGroup": "Consumer Services",
    "securityType": 1,
    "volume": 17143,
    "statusCode": "",
    "isin": "AU0000157075",
    "priceClose": 0.36,
    "priceDayHigh": 0.38,
    "priceDayLow": 0.365,
    "priceFiftyTwoWeekHigh": 1.52,
    "priceFiftyTwoWeekLow": 0.36,
    "volumeAverage": 136158.274725,
    "cashFlow": -7.598,
    "earningsPerShare": -0.03034,
    "freeCashFlowYield": -0.0000100000010000001,
    "priceEarningsRatio": -99999.99,
    "priceToCash": -99999.99,
    "foreignExempt": false,
    "shareDescription": "Ordinary Fully Paid",
    "numOfShares": 200201228,
    "yieldAnnual": 0,
    "incomeStatement": [
      {
        "revenue": 49853000,
        "netIncome": -6071000,
        "period": "2022A",
        "fPeriodEndDate": 44742,
        "curCode": "AUD"
      },
      {
        "revenue": 32351000,
        "netIncome": 2979000,
        "period": "2021A",
        "fPeriodEndDate": 44377,
        "curCode": "AUD"
      },
      {
        "revenue": 16808130,
        "netIncome": 4484600,
        "period": "2020A",
        "fPeriodEndDate": 44012,
        "curCode": "AUD"
      },
      {
        "revenue": 9574830,
        "netIncome": -373720,
        "period": "2019A",
        "fPeriodEndDate": 43646,
        "curCode": "AUD"
      }
    ]
  },
  {
    "symbol": "CLU",
    "displayName": "CLUEY LTD",
    "industry": "Consumer Services",
    "dateListed": "2020-12-09",
    "marketCap": 63608907,
    "xid": "626345102",
    "priceChangeFiveDayPercent": 1.0989010989010999,
    "isRecentListing": false,
    "priceAsk": 0.485,
    "priceBid": 0.41000000000000003,
    "priceChange": 0,
    "priceChangePercent": 0,
    "priceLast": 0.46,
    "sector": "Consumer Discretionary",
    "industryGroup": "Consumer Services",
    "securityType": 1,
    "volume": 0,
    "statusCode": "",
    "isin": "AU0000113490",
    "priceClose": 0.46,
    "priceFiftyTwoWeekHigh": 1.125,
    "priceFiftyTwoWeekLow": 0.4,
    "volumeAverage": 35564.048387,
    "cashFlow": -17.5655,
    "earningsPerShare": -0.15946,
    "freeCashFlowYield": -0.0000100000010000001,
    "priceEarningsRatio": -99999.99,
    "priceToCash": -99999.99,
    "foreignExempt": false,
    "shareDescription": "Ordinary Fully Paid",
    "numOfShares": 138280233,
    "yieldAnnual": 0,
    "incomeStatement": [
      {
        "revenue": 34328100,
        "netIncome": -20897200,
        "period": "2022A",
        "fPeriodEndDate": 44742,
        "curCode": "AUD"
      },
      {
        "revenue": 10157860,
        "netIncome": -11907610,
        "period": "2021A",
        "fPeriodEndDate": 44377,
        "curCode": "AUD"
      },
      {
        "revenue": 5029920,
        "netIncome": -15232860,
        "period": "2020A",
        "fPeriodEndDate": 44012,
        "curCode": "AUD"
      },
      {
        "revenue": 900760,
        "netIncome": -10003000,
        "period": "2019A",
        "fPeriodEndDate": 43646,
        "curCode": "AUD"
      }
    ]
  },
  {
    "symbol": "CKF",
    "displayName": "COLLINS FOODS LIMITED",
    "industry": "Consumer Services",
    "dateListed": "2011-08-04",
    "marketCap": 829470584,
    "xid": "35887434",
    "priceChangeFiveDayPercent": 1.6973125884016989,
    "isRecentListing": false,
    "priceAsk": 7.23,
    "priceBid": 7.12,
    "priceChange": 0.1200000000000001,
    "priceChangePercent": 1.6973125884016989,
    "priceLast": 7.19,
    "sector": "Consumer Discretionary",
    "industryGroup": "Consumer Services",
    "securityType": 1,
    "volume": 224174,
    "upcomingEventName": "Collins Foods Limited 2023 AGM",
    "statusCode": "",
    "isin": "AU000000CKF7",
    "priceClose": 7.07,
    "priceDayHigh": 7.23,
    "priceDayLow": 7.11,
    "priceFiftyTwoWeekHigh": 13.66,
    "priceFiftyTwoWeekLow": 6.96,
    "volumeAverage": 394912.472527,
    "dateExDate": "2022-12-05",
    "datePayDate": "2022-12-29",
    "dateRecordDate": "2022-12-06",
    "dividend": 0.12,
    "dividendType": "I",
    "frankingPercent": 100,
    "cashFlow": 56.751,
    "earningsPerShare": 0.3358,
    "freeCashFlowYield": -0.0000100000010000001,
    "priceEarningsRatio": 21.41155,
    "priceToCash": -99999.99,
    "foreignExempt": false,
    "shareDescription": "Ordinary Fully Paid",
    "numOfShares": 117322572,
    "yieldAnnual": 3.755215577190542,
    "incomeStatement": [
      {
        "revenue": 1184521000,
        "netIncome": 54799000,
        "period": "2022A",
        "fPeriodEndDate": 44682,
        "curCode": "AUD"
      },
      {
        "revenue": 1065905000,
        "netIncome": 32608000,
        "period": "2021A",
        "fPeriodEndDate": 44318,
        "curCode": "AUD"
      },
      {
        "revenue": 948088000,
        "netIncome": 31263000,
        "period": "2020A",
        "fPeriodEndDate": 43954,
        "curCode": "AUD"
      },
      {
        "revenue": 901215000,
        "netIncome": 39111000,
        "period": "2019A",
        "fPeriodEndDate": 43583,
        "curCode": "AUD"
      }
    ]
  },
  {
    "symbol": "CTD",
    "displayName": "CORPORATE TRAVEL MANAGEMENT LIMITED",
    "industry": "Consumer Services",
    "dateListed": "2010-12-15",
    "marketCap": 2118796802,
    "xid": "27528971",
    "priceChangeFiveDayPercent": 0.40899795501022834,
    "isRecentListing": false,
    "priceAsk": 14.85,
    "priceBid": 14.620000000000001,
    "priceChange": 0.25,
    "priceChangePercent": 1.7265193370165746,
    "priceLast": 14.73,
    "sector": "Consumer Discretionary",
    "industryGroup": "Consumer Services",
    "securityType": 1,
    "volume": 273090,
    "statusCode": "",
    "isin": "AU000000CTD3",
    "priceClose": 14.48,
    "priceDayHigh": 14.84,
    "priceDayLow": 14.55,
    "priceFiftyTwoWeekHigh": 26.34,
    "priceFiftyTwoWeekLow": 13.72,
    "volumeAverage": 492331.054945,
    "dateExDate": "2022-09-05",
    "datePayDate": "2022-10-05",
    "dateRecordDate": "2022-09-06",
    "dividend": 0.05,
    "dividendType": "F",
    "frankingPercent": 0,
    "cashFlow": 47.951,
    "earningsPerShare": 0.01907,
    "freeCashFlowYield": 0.025496688235165134,
    "priceEarningsRatio": 772.4174,
    "priceToCash": 39.22078,
    "foreignExempt": false,
    "shareDescription": "Ordinary Fully Paid",
    "numOfShares": 146325746,
    "yieldAnnual": 0.3394433129667345,
    "incomeStatement": [
      {
        "revenue": 377360000,
        "netIncome": 3101000,
        "period": "2022A",
        "fPeriodEndDate": 44742,
        "curCode": "AUD"
      },
      {
        "revenue": 174046000,
        "netIncome": -55351000,
        "period": "2021A",
        "fPeriodEndDate": 44377,
        "curCode": "AUD"
      },
      {
        "revenue": 316364000,
        "netIncome": -8185000,
        "period": "2020A",
        "fPeriodEndDate": 44012,
        "curCode": "AUD"
      },
      {
        "revenue": 446739000,
        "netIncome": 86235000,
        "period": "2019A",
        "fPeriodEndDate": 43646,
        "curCode": "AUD"
      }
    ]
  },
  {
    "symbol": "DMP",
    "displayName": "DOMINO'S PIZZA ENTERPRISES LIMITED",
    "industry": "Consumer Services",
    "dateListed": "2005-05-16",
    "marketCap": 5851371300,
    "xid": "1745764",
    "priceChangeFiveDayPercent": 1.9073988617135744,
    "isRecentListing": false,
    "priceAsk": 66.66,
    "priceBid": 65.68,
    "priceChange": 0.5699999999999932,
    "priceChangePercent": 0.867844092570026,
    "priceLast": 66.25,
    "sector": "Consumer Discretionary",
    "industryGroup": "Consumer Services",
    "securityType": 1,
    "volume": 148272,
    "statusCode": "",
    "isin": "AU000000DMP0",
    "priceClose": 65.68,
    "priceDayHigh": 66.94,
    "priceDayLow": 65.74,
    "priceFiftyTwoWeekHigh": 123.33,
    "priceFiftyTwoWeekLow": 49.83,
    "volumeAverage": 616402.588889,
    "dateExDate": "2022-08-30",
    "datePayDate": "2022-09-15",
    "dateRecordDate": "2022-08-31",
    "dividend": 0.681,
    "dividendType": "F",
    "frankingPercent": 70,
    "cashFlow": -152.096,
    "earningsPerShare": 1.82887,
    "freeCashFlowYield": 0.05102306344513847,
    "priceEarningsRatio": 36.22455,
    "priceToCash": 19.59898,
    "foreignExempt": false,
    "shareDescription": "Ordinary Fully Paid",
    "numOfShares": 89089088,
    "yieldAnnual": 2.362264150943396,
    "incomeStatement": [
      {
        "revenue": 2289268000,
        "netIncome": 158716000,
        "period": "2022A",
        "fPeriodEndDate": 44745,
        "curCode": "AUD"
      },
      {
        "revenue": 2199106000,
        "netIncome": 184477000,
        "period": "2021A",
        "fPeriodEndDate": 44374,
        "curCode": "AUD"
      },
      {
        "revenue": 1905261000,
        "netIncome": 138483000,
        "period": "2020A",
        "fPeriodEndDate": 44010,
        "curCode": "AUD"
      },
      {
        "revenue": 1435410000,
        "netIncome": 115912000,
        "period": "2019A",
        "fPeriodEndDate": 43646,
        "curCode": "AUD"
      }
    ]
  },
  {
    "symbol": "DNA",
    "displayName": "DONACO INTERNATIONAL LIMITED",
    "industry": "Consumer Services",
    "dateListed": "2004-12-23",
    "marketCap": 64857943,
    "xid": "273597",
    "priceChangeFiveDayPercent": 4.0000000000000036,
    "isRecentListing": false,
    "priceAsk": 0.054,
    "priceBid": 0.052000000000000005,
    "priceChange": -0.0005000000000000004,
    "priceChangePercent": -0.9523809523809531,
    "priceLast": 0.052000000000000005,
    "sector": "Consumer Discretionary",
    "industryGroup": "Consumer Services",
    "securityType": 1,
    "volume": 259005,
    "statusCode": "",
    "isin": "AU000000DNA0",
    "priceClose": 0.052500000000000005,
    "priceDayHigh": 0.054,
    "priceDayLow": 0.051500000000000004,
    "priceFiftyTwoWeekHigh": 0.065,
    "priceFiftyTwoWeekLow": 0.029,
    "volumeAverage": 384066.384615,
    "dateExDate": "2017-10-05",
    "datePayDate": "2017-10-20",
    "dateRecordDate": "2017-10-06",
    "dividend": 0.005,
    "dividendType": "F",
    "frankingPercent": 0,
    "cashFlow": -5.71284,
    "earningsPerShare": -0.01335,
    "freeCashFlowYield": -0.0000100000010000001,
    "priceEarningsRatio": -99999.99,
    "priceToCash": -99999.99,
    "foreignExempt": false,
    "shareDescription": "Ordinary Fully Paid",
    "numOfShares": 1235389382,
    "yieldAnnual": 0,
    "incomeStatement": [
      {
        "revenue": 2437090,
        "netIncome": -16491630,
        "period": "2022A",
        "fPeriodEndDate": 44742,
        "curCode": "AUD"
      },
      {
        "revenue": 10319470,
        "netIncome": 25177130,
        "period": "2021A",
        "fPeriodEndDate": 44377,
        "curCode": "AUD"
      },
      {
        "revenue": 53485040,
        "netIncome": -58885430,
        "period": "2020A",
        "fPeriodEndDate": 44012,
        "curCode": "AUD"
      },
      {
        "revenue": 86263580,
        "netIncome": -198014600,
        "period": "2019A",
        "fPeriodEndDate": 43646,
        "curCode": "AUD"
      }
    ]
  },
  {
    "symbol": "EDU",
    "displayName": "EDU HOLDINGS LIMITED",
    "industry": "Consumer Services",
    "dateListed": "2004-06-25",
    "marketCap": 28912528,
    "xid": "275635",
    "priceChangeFiveDayPercent": 1.5860328923216522e-14,
    "isRecentListing": false,
    "priceAsk": 0.2,
    "priceBid": 0.18,
    "priceChange": 0,
    "priceChangePercent": 0,
    "priceLast": 0.17500000000000002,
    "sector": "Consumer Discretionary",
    "industryGroup": "Consumer Services",
    "securityType": 1,
    "volume": 0,
    "statusCode": "",
    "isin": "AU0000198483",
    "priceClose": 0.17500000000000002,
    "priceFiftyTwoWeekHigh": 0.2,
    "priceFiftyTwoWeekLow": 0.12,
    "volumeAverage": 92678.580645,
    "dateExDate": "2010-03-05",
    "datePayDate": "2010-04-09",
    "dateRecordDate": "2010-03-12",
    "dividend": 0.0125,
    "dividendType": "I",
    "frankingPercent": 100,
    "cashFlow": -1.97642,
    "earningsPerShare": -0.01078,
    "freeCashFlowYield": 0.028665426600311936,
    "priceEarningsRatio": -99999.99,
    "priceToCash": 34.88523,
    "foreignExempt": false,
    "shareDescription": "Ordinary Fully Paid",
    "numOfShares": 165214443,
    "yieldAnnual": 0,
    "incomeStatement": [
      {
        "revenue": 10399230,
        "netIncome": 766370,
        "period": "2021A",
        "fPeriodEndDate": 44561,
        "curCode": "AUD"
      },
      {
        "revenue": 25305010,
        "netIncome": -4587550,
        "period": "2020A",
        "fPeriodEndDate": 44012,
        "curCode": "AUD"
      },
      {
        "revenue": 22002900,
        "netIncome": 952250,
        "period": "2019A",
        "fPeriodEndDate": 43646,
        "curCode": "AUD"
      },
      {
        "revenue": 12552020,
        "netIncome": 24940,
        "period": "2018A",
        "fPeriodEndDate": 43281,
        "curCode": "AUD"
      }
    ]
  },
  {
    "symbol": "ENN",
    "displayName": "ELANOR INVESTORS GROUP",
    "industry": "Consumer Services",
    "dateListed": "2014-07-11",
    "marketCap": 204599588,
    "xid": "76484697",
    "priceChangeFiveDayPercent": -6.051873198847261,
    "isRecentListing": false,
    "priceAsk": 1.7,
    "priceBid": 1.6300000000000001,
    "priceChange": -0.030000000000000027,
    "priceChangePercent": -1.807228915662652,
    "priceLast": 1.6300000000000001,
    "sector": "Consumer Discretionary",
    "industryGroup": "Consumer Services",
    "securityType": 6,
    "volume": 24585,
    "statusCode": "XD",
    "isin": "AU000000ENN1",
    "priceClose": 1.6600000000000001,
    "priceDayHigh": 1.7,
    "priceDayLow": 1.6300000000000001,
    "priceFiftyTwoWeekHigh": 2.31,
    "priceFiftyTwoWeekLow": 1.49,
    "volumeAverage": 44214.933333,
    "dateExDate": "2022-12-29",
    "datePayDate": "2023-02-28",
    "dateRecordDate": "2022-12-30",
    "dividend": 0.073,
    "dividendType": "I",
    "frankingPercent": 0,
    "cashFlow": -54.18,
    "earningsPerShare": 0.00132,
    "freeCashFlowYield": 0.043623260795121174,
    "priceEarningsRatio": 1234.849,
    "priceToCash": 22.92355,
    "foreignExempt": false,
    "shareDescription": "Fully Paid Ordinary/units Stapled Securities",
    "numOfShares": 123252764,
    "yieldAnnual": 7.196319018404908,
    "incomeStatement": [
      {
        "revenue": 92164000,
        "netIncome": 966000,
        "period": "2022A",
        "fPeriodEndDate": 44742,
        "curCode": "AUD"
      },
      {
        "revenue": 82633000,
        "netIncome": 7858000,
        "period": "2021A",
        "fPeriodEndDate": 44377,
        "curCode": "AUD"
      },
      {
        "revenue": 66459000,
        "netIncome": -18329000,
        "period": "2020A",
        "fPeriodEndDate": 44012,
        "curCode": "AUD"
      },
      {
        "revenue": 109600000,
        "netIncome": 15522000,
        "period": "2019A",
        "fPeriodEndDate": 43646,
        "curCode": "AUD"
      }
    ]
  },
  {
    "symbol": "EVO",
    "displayName": "EMBARK EDUCATION LIMITED",
    "industry": "Consumer Services",
    "dateListed": "2014-12-05",
    "marketCap": 84561227,
    "xid": "81389048",
    "priceChangeFiveDayPercent": 1.8867924528301903,
    "isRecentListing": false,
    "priceAsk": 0.55,
    "priceBid": 0.51,
    "priceChange": 0.010000000000000009,
    "priceChangePercent": 1.8867924528301903,
    "priceLast": 0.54,
    "sector": "Consumer Discretionary",
    "industryGroup": "Consumer Services",
    "securityType": 1,
    "volume": 39385,
    "statusCode": "",
    "isin": "NZEVOE0001S4",
    "priceClose": 0.53,
    "priceDayHigh": 0.54,
    "priceDayLow": 0.54,
    "priceFiftyTwoWeekHigh": 0.87,
    "priceFiftyTwoWeekLow": 0.465,
    "volumeAverage": 75308.903614,
    "dateExDate": "2022-11-23",
    "datePayDate": "2022-12-08",
    "dateRecordDate": "2022-11-24",
    "dividend": 0.0324,
    "dividendType": "I",
    "frankingPercent": 0,
    "cashFlow": -99999.99,
    "earningsPerShare": -0.00703,
    "freeCashFlowYield": 0.15419962683690305,
    "priceEarningsRatio": -99999.99,
    "priceToCash": 6.4851,
    "foreignExempt": true,
    "shareDescription": "Ordinary Fully Paid Foreign Exempt Nzx",
    "numOfShares": 159549484,
    "yieldAnnual": 0,
    "incomeStatement": [
      {
        "revenue": 157959000,
        "netIncome": 741000,
        "period": "2021A",
        "fPeriodEndDate": 44561,
        "curCode": "NZD"
      },
      {
        "revenue": 102639000,
        "netIncome": 7570000,
        "period": "2020A",
        "fPeriodEndDate": 44196,
        "curCode": "NZD"
      },
      {
        "revenue": 137177000,
        "netIncome": -101554000,
        "period": "2019A",
        "fPeriodEndDate": 43555,
        "curCode": "NZD"
      },
      {
        "revenue": 138395000,
        "netIncome": -4213000,
        "period": "2018A",
        "fPeriodEndDate": 43190,
        "curCode": "NZD"
      }
    ]
  },
  {
    "symbol": "EBG",
    "displayName": "EUMUNDI GROUP LIMITED",
    "industry": "Consumer Services",
    "dateListed": "1989-12-07",
    "marketCap": 47107786,
    "xid": "94997",
    "priceChangeFiveDayPercent": 0,
    "isRecentListing": false,
    "priceAsk": 1.12,
    "priceBid": 1.07,
    "priceChange": 0,
    "priceChangePercent": 0,
    "priceLast": 1.065,
    "sector": "Consumer Discretionary",
    "industryGroup": "Consumer Services",
    "securityType": 1,
    "volume": 0,
    "statusCode": "",
    "isin": "AU000000EBG0",
    "priceClose": 1.065,
    "priceFiftyTwoWeekHigh": 1.145,
    "priceFiftyTwoWeekLow": 1,
    "volumeAverage": 7544.185185,
    "dateExDate": "2022-09-01",
    "datePayDate": "2022-09-13",
    "dateRecordDate": "2022-09-02",
    "dividend": 0.035,
    "dividendType": "F",
    "frankingPercent": 100,
    "cashFlow": 3.979,
    "earningsPerShare": 0.16749,
    "freeCashFlowYield": 0.18697530056279568,
    "priceEarningsRatio": 6.35859,
    "priceToCash": 5.3483,
    "foreignExempt": false,
    "shareDescription": "Ordinary Fully Paid",
    "numOfShares": 44232663,
    "yieldAnnual": 6.572769953051643,
    "incomeStatement": [
      {
        "revenue": 27684000,
        "netIncome": 7022000,
        "period": "2022A",
        "fPeriodEndDate": 44742,
        "curCode": "AUD"
      },
      {
        "revenue": 26216000,
        "netIncome": 4263000,
        "period": "2021A",
        "fPeriodEndDate": 44377,
        "curCode": "AUD"
      },
      {
        "revenue": 20715000,
        "netIncome": -1022000,
        "period": "2020A",
        "fPeriodEndDate": 44012,
        "curCode": "AUD"
      },
      {
        "revenue": 24938000,
        "netIncome": 1974000,
        "period": "2019A",
        "fPeriodEndDate": 43646,
        "curCode": "AUD"
      }
    ]
  },
  {
    "symbol": "EXP",
    "displayName": "EXPERIENCE CO LIMITED",
    "industry": "Consumer Services",
    "dateListed": "2015-03-27",
    "marketCap": 165880752,
    "xid": "86313930",
    "priceChangeFiveDayPercent": 0,
    "isRecentListing": false,
    "priceAsk": 0.23,
    "priceBid": 0.215,
    "priceChange": 0.010000000000000009,
    "priceChangePercent": 4.545454545454549,
    "priceLast": 0.23,
    "sector": "Consumer Discretionary",
    "industryGroup": "Consumer Services",
    "securityType": 1,
    "volume": 285113,
    "statusCode": "",
    "isin": "AU000000EXP5",
    "priceClose": 0.22,
    "priceDayHigh": 0.23,
    "priceDayLow": 0.22,
    "priceFiftyTwoWeekHigh": 0.355,
    "priceFiftyTwoWeekLow": 0.175,
    "volumeAverage": 738386.141026,
    "dateExDate": "2018-09-14",
    "datePayDate": "2018-09-28",
    "dateRecordDate": "2018-09-17",
    "dividend": 0.01,
    "dividendType": "F",
    "frankingPercent": 100,
    "cashFlow": -4.84,
    "earningsPerShare": -0.02006,
    "freeCashFlowYield": -0.0000100000010000001,
    "priceEarningsRatio": -99999.99,
    "priceToCash": -99999.99,
    "foreignExempt": false,
    "shareDescription": "Ordinary Fully Paid",
    "numOfShares": 754003418,
    "yieldAnnual": 0,
    "incomeStatement": [
      {
        "revenue": 55818000,
        "netIncome": -13583000,
        "period": "2022A",
        "fPeriodEndDate": 44742,
        "curCode": "AUD"
      },
      {
        "revenue": 44449000,
        "netIncome": -4301000,
        "period": "2021A",
        "fPeriodEndDate": 44377,
        "curCode": "AUD"
      },
      {
        "revenue": 87402000,
        "netIncome": -51413000,
        "period": "2020A",
        "fPeriodEndDate": 44012,
        "curCode": "AUD"
      },
      {
        "revenue": 130005000,
        "netIncome": -48258000,
        "period": "2019A",
        "fPeriodEndDate": 43646,
        "curCode": "AUD"
      }
    ]
  },
  {
    "symbol": "FLT",
    "displayName": "FLIGHT CENTRE TRAVEL GROUP LIMITED",
    "industry": "Consumer Services",
    "dateListed": "1995-12-01",
    "marketCap": 2842194241,
    "xid": "108040",
    "priceChangeFiveDayPercent": 0.20746887966804536,
    "isRecentListing": false,
    "priceAsk": 14.540000000000001,
    "priceBid": 14.43,
    "priceChange": 0.28999999999999915,
    "priceChangePercent": 2.0422535211267543,
    "priceLast": 14.49,
    "sector": "Consumer Discretionary",
    "industryGroup": "Consumer Services",
    "securityType": 1,
    "volume": 557214,
    "statusCode": "",
    "isin": "AU000000FLT9",
    "priceClose": 14.200000000000001,
    "priceDayHigh": 14.6,
    "priceDayLow": 14.35,
    "priceFiftyTwoWeekHigh": 23.38,
    "priceFiftyTwoWeekLow": 13.86,
    "volumeAverage": 1197457.505495,
    "dateExDate": "2019-09-12",
    "datePayDate": "2019-10-11",
    "dateRecordDate": "2019-09-13",
    "dividend": 0.98,
    "dividendType": "F",
    "frankingPercent": 100,
    "cashFlow": -141.745,
    "earningsPerShare": -1.43685,
    "freeCashFlowYield": -0.0000100000010000001,
    "priceEarningsRatio": -99999.99,
    "priceToCash": -99999.99,
    "foreignExempt": false,
    "shareDescription": "Ordinary Fully Paid",
    "numOfShares": 200154524,
    "yieldAnnual": 0,
    "incomeStatement": [
      {
        "revenue": 1007485000,
        "netIncome": -286651000,
        "period": "2022A",
        "fPeriodEndDate": 44742,
        "curCode": "AUD"
      },
      {
        "revenue": 395907000,
        "netIncome": -433129000,
        "period": "2021A",
        "fPeriodEndDate": 44377,
        "curCode": "AUD"
      },
      {
        "revenue": 1897272000,
        "netIncome": -662285000,
        "period": "2020A",
        "fPeriodEndDate": 44012,
        "curCode": "AUD"
      },
      {
        "revenue": 3055268000,
        "netIncome": 263825000,
        "period": "2019A",
        "fPeriodEndDate": 43646,
        "curCode": "AUD"
      }
    ]
  },
  {
    "symbol": "GEM",
    "displayName": "G8 EDUCATION LIMITED",
    "industry": "Consumer Services",
    "dateListed": "2007-12-05",
    "marketCap": 949077153,
    "xid": "9231396",
    "priceChangeFiveDayPercent": -3.493449781659392,
    "isRecentListing": false,
    "priceAsk": 1.1300000000000001,
    "priceBid": 1.1,
    "priceChange": -0.015000000000000124,
    "priceChangePercent": -1.3392857142857253,
    "priceLast": 1.105,
    "sector": "Consumer Discretionary",
    "industryGroup": "Consumer Services",
    "securityType": 1,
    "volume": 576637,
    "statusCode": "",
    "isin": "AU000000GEM7",
    "priceClose": 1.12,
    "priceDayHigh": 1.1400000000000001,
    "priceDayLow": 1.105,
    "priceFiftyTwoWeekHigh": 1.33,
    "priceFiftyTwoWeekLow": 0.9025,
    "volumeAverage": 1248402.395604,
    "dateExDate": "2022-09-08",
    "datePayDate": "2022-10-07",
    "dateRecordDate": "2022-09-09",
    "dividend": 0.01,
    "dividendType": "I",
    "frankingPercent": 100,
    "cashFlow": 1.957,
    "earningsPerShare": 0.03415,
    "freeCashFlowYield": 0.12814105767629008,
    "priceEarningsRatio": 32.35725,
    "priceToCash": 7.8039,
    "foreignExempt": false,
    "shareDescription": "Ordinary Fully Paid",
    "numOfShares": 847390315,
    "yieldAnnual": 3.619909502262443,
    "incomeStatement": [
      {
        "revenue": 845073000,
        "netIncome": 45681000,
        "period": "2021A",
        "fPeriodEndDate": 44561,
        "curCode": "AUD"
      },
      {
        "revenue": 616186000,
        "netIncome": -188970000,
        "period": "2020A",
        "fPeriodEndDate": 44196,
        "curCode": "AUD"
      },
      {
        "revenue": 916622000,
        "netIncome": 52019000,
        "period": "2019A",
        "fPeriodEndDate": 43830,
        "curCode": "AUD"
      },
      {
        "revenue": 851530000,
        "netIncome": 71831000,
        "period": "2018A",
        "fPeriodEndDate": 43465,
        "curCode": "AUD"
      }
    ]
  },
  {
    "symbol": "HLO",
    "displayName": "HELLOWORLD TRAVEL LIMITED",
    "industry": "Consumer Services",
    "dateListed": "2000-09-13",
    "marketCap": 203861616,
    "xid": "172915",
    "priceChangeFiveDayPercent": -0.7407407407407414,
    "isRecentListing": false,
    "priceAsk": 1.35,
    "priceBid": 1.34,
    "priceChange": 0.025000000000000133,
    "priceChangePercent": 1.9011406844106566,
    "priceLast": 1.34,
    "sector": "Consumer Discretionary",
    "industryGroup": "Consumer Services",
    "securityType": 1,
    "volume": 305683,
    "statusCode": "",
    "isin": "AU000000HLO6",
    "priceClose": 1.315,
    "priceDayHigh": 1.345,
    "priceDayLow": 1.32,
    "priceFiftyTwoWeekHigh": 2.87,
    "priceFiftyTwoWeekLow": 1.3,
    "volumeAverage": 277473.989011,
    "dateExDate": "2022-09-02",
    "datePayDate": "2022-09-23",
    "dateRecordDate": "2022-09-05",
    "dividend": 0.1,
    "dividendType": "F",
    "frankingPercent": 100,
    "cashFlow": -20.239,
    "earningsPerShare": -0.18128,
    "freeCashFlowYield": -0.0000100000010000001,
    "priceEarningsRatio": -99999.99,
    "priceToCash": -99999.99,
    "foreignExempt": false,
    "shareDescription": "Ordinary Fully Paid",
    "numOfShares": 155027845,
    "yieldAnnual": 7.462686567164179,
    "incomeStatement": [
      {
        "revenue": 67364000,
        "netIncome": 90527000,
        "period": "2022A",
        "fPeriodEndDate": 44742,
        "curCode": "AUD"
      },
      {
        "revenue": 57498000,
        "netIncome": -35496000,
        "period": "2021A",
        "fPeriodEndDate": 44377,
        "curCode": "AUD"
      },
      {
        "revenue": 294879000,
        "netIncome": -69874000,
        "period": "2020A",
        "fPeriodEndDate": 44012,
        "curCode": "AUD"
      },
      {
        "revenue": 357562000,
        "netIncome": 38008000,
        "period": "2019A",
        "fPeriodEndDate": 43646,
        "curCode": "AUD"
      }
    ]
  },
  {
    "symbol": "HRO",
    "displayName": "HIRO BRANDS LIMITED",
    "industry": "Consumer Services",
    "dateListed": "2016-01-14",
    "marketCap": -1,
    "xid": "633092831",
    "priceChangeFiveDayPercent": 0,
    "isRecentListing": false,
    "priceChange": 0,
    "priceChangePercent": 0,
    "priceLast": 0.068,
    "sector": "Consumer Discretionary",
    "industryGroup": "Consumer Services",
    "securityType": 1,
    "volume": 0,
    "statusCode": "RE",
    "isin": "AU0000240053",
    "priceClose": 0.068,
    "priceFiftyTwoWeekHigh": 0.07100000000000001,
    "priceFiftyTwoWeekLow": 0.065,
    "cashFlow": -1.98855,
    "earningsPerShare": 0.03922,
    "freeCashFlowYield": 1.1382780130219006,
    "priceEarningsRatio": -99999.99,
    "priceToCash": 0.87852,
    "foreignExempt": false,
    "shareDescription": "Ordinary Fully Paid",
    "numOfShares": 2082542,
    "yieldAnnual": 0,
    "incomeStatement": [
      {
        "revenue": 8017720,
        "netIncome": 5427820,
        "period": "2022A",
        "fPeriodEndDate": 44742,
        "curCode": "AUD"
      },
      {
        "revenue": 5042000,
        "netIncome": -11923000,
        "period": "2021A",
        "fPeriodEndDate": 44377,
        "curCode": "AUD"
      },
      {
        "revenue": 10793000,
        "netIncome": -11786000,
        "period": "2020A",
        "fPeriodEndDate": 44012,
        "curCode": "AUD"
      },
      {
        "revenue": 9967000,
        "netIncome": -13552000,
        "period": "2019A",
        "fPeriodEndDate": 43646,
        "curCode": "AUD"
      }
    ]
  },
  {
    "symbol": "IEL",
    "displayName": "IDP EDUCATION LIMITED",
    "industry": "Consumer Services",
    "dateListed": "2015-11-26",
    "marketCap": 7567961577,
    "xid": "318107285",
    "priceChangeFiveDayPercent": 0.14738393515106538,
    "isRecentListing": false,
    "priceAsk": 27.3,
    "priceBid": 26.900000000000002,
    "priceChange": -0.010000000000001563,
    "priceChangePercent": -0.0367782272894504,
    "priceLast": 27.18,
    "sector": "Consumer Discretionary",
    "industryGroup": "Consumer Services",
    "securityType": 1,
    "volume": 604981,
    "statusCode": "",
    "isin": "AU000000IEL5",
    "priceClose": 27.19,
    "priceDayHigh": 27.59,
    "priceDayLow": 26.92,
    "priceFiftyTwoWeekHigh": 35.68,
    "priceFiftyTwoWeekLow": 20.53,
    "volumeAverage": 869632.967033,
    "dateExDate": "2022-09-07",
    "datePayDate": "2022-09-29",
    "dateRecordDate": "2022-09-08",
    "dividend": 0.135,
    "dividendType": "F",
    "frankingPercent": 14,
    "cashFlow": 73.411,
    "earningsPerShare": 0.36792,
    "freeCashFlowYield": 0.01864701718583692,
    "priceEarningsRatio": 73.87476,
    "priceToCash": 53.62788,
    "foreignExempt": false,
    "shareDescription": "Ordinary Fully Paid",
    "numOfShares": 278336211,
    "yieldAnnual": 0.9933774834437086,
    "incomeStatement": [
      {
        "revenue": 793331000,
        "netIncome": 102604000,
        "period": "2022A",
        "fPeriodEndDate": 44742,
        "curCode": "AUD"
      },
      {
        "revenue": 528742000,
        "netIncome": 39683000,
        "period": "2021A",
        "fPeriodEndDate": 44377,
        "curCode": "AUD"
      },
      {
        "revenue": 587106000,
        "netIncome": 68110000,
        "period": "2020A",
        "fPeriodEndDate": 44012,
        "curCode": "AUD"
      },
      {
        "revenue": 598136000,
        "netIncome": 66627000,
        "period": "2019A",
        "fPeriodEndDate": 43646,
        "curCode": "AUD"
      }
    ]
  },
  {
    "symbol": "IVC",
    "displayName": "INVOCARE LIMITED",
    "industry": "Consumer Services",
    "dateListed": "2003-12-04",
    "marketCap": 1571702597,
    "xid": "170912",
    "priceChangeFiveDayPercent": 0.5469462169553211,
    "isRecentListing": false,
    "priceAsk": 11.11,
    "priceBid": 10.86,
    "priceChange": 0.11999999999999922,
    "priceChangePercent": 1.0999083409715784,
    "priceLast": 11.03,
    "sector": "Consumer Discretionary",
    "industryGroup": "Consumer Services",
    "securityType": 1,
    "volume": 116722,
    "statusCode": "",
    "isin": "AU000000IVC8",
    "priceClose": 10.91,
    "priceDayHigh": 11.08,
    "priceDayLow": 10.950000000000001,
    "priceFiftyTwoWeekHigh": 13.19,
    "priceFiftyTwoWeekLow": 9.72,
    "volumeAverage": 232837.835165,
    "dateExDate": "2022-09-01",
    "datePayDate": "2022-10-06",
    "dateRecordDate": "2022-09-02",
    "dividend": 0.135,
    "dividendType": "I",
    "frankingPercent": 100,
    "cashFlow": -19.415,
    "earningsPerShare": 0.13605,
    "freeCashFlowYield": 0.04180392288012308,
    "priceEarningsRatio": 81.07313,
    "priceToCash": 23.9212,
    "foreignExempt": false,
    "shareDescription": "Ordinary Fully Paid",
    "numOfShares": 144060733,
    "yieldAnnual": 2.2665457842248413,
    "incomeStatement": [
      {
        "revenue": 531604000,
        "netIncome": 80158000,
        "period": "2021A",
        "fPeriodEndDate": 44561,
        "curCode": "AUD"
      },
      {
        "revenue": 475217000,
        "netIncome": -11542000,
        "period": "2020A",
        "fPeriodEndDate": 44196,
        "curCode": "AUD"
      },
      {
        "revenue": 500348000,
        "netIncome": 63752000,
        "period": "2019A",
        "fPeriodEndDate": 43830,
        "curCode": "AUD"
      },
      {
        "revenue": 480797000,
        "netIncome": 41224000,
        "period": "2018A",
        "fPeriodEndDate": 43465,
        "curCode": "AUD"
      }
    ]
  },
  {
    "symbol": "JIN",
    "displayName": "JUMBO INTERACTIVE LIMITED",
    "industry": "Consumer Services",
    "dateListed": "1972-06-14",
    "marketCap": 882146714,
    "xid": "175177",
    "priceChangeFiveDayPercent": -1.2014134275618369,
    "isRecentListing": false,
    "priceAsk": 14.41,
    "priceBid": 13.950000000000001,
    "priceChange": -0.03999999999999915,
    "priceChangePercent": -0.28530670470755454,
    "priceLast": 13.98,
    "sector": "Consumer Discretionary",
    "industryGroup": "Consumer Services",
    "securityType": 1,
    "volume": 67908,
    "statusCode": "",
    "isin": "AU000000JIN0",
    "priceClose": 14.02,
    "priceDayHigh": 14.32,
    "priceDayLow": 13.98,
    "priceFiftyTwoWeekHigh": 19.94,
    "priceFiftyTwoWeekLow": 11.42,
    "volumeAverage": 114661.010989,
    "dateExDate": "2022-09-01",
    "datePayDate": "2022-09-23",
    "dateRecordDate": "2022-09-02",
    "dividend": 0.205,
    "dividendType": "F",
    "frankingPercent": 100,
    "cashFlow": 12.856,
    "earningsPerShare": 0.49336,
    "freeCashFlowYield": 0.04661961193835023,
    "priceEarningsRatio": 28.33631,
    "priceToCash": 21.4502,
    "foreignExempt": false,
    "shareDescription": "Ordinary Fully Paid",
    "numOfShares": 62920593,
    "yieldAnnual": 3.040057224606581,
    "incomeStatement": [
      {
        "revenue": 104314000,
        "netIncome": 31176000,
        "period": "2022A",
        "fPeriodEndDate": 44742,
        "curCode": "AUD"
      },
      {
        "revenue": 83504000,
        "netIncome": 26959000,
        "period": "2021A",
        "fPeriodEndDate": 44377,
        "curCode": "AUD"
      },
      {
        "revenue": 72144000,
        "netIncome": 25883000,
        "period": "2020A",
        "fPeriodEndDate": 44012,
        "curCode": "AUD"
      },
      {
        "revenue": 66675000,
        "netIncome": 26420000,
        "period": "2019A",
        "fPeriodEndDate": 43646,
        "curCode": "AUD"
      }
    ]
  },
  {
    "symbol": "KLS",
    "displayName": "KELSIAN GROUP LIMITED",
    "industry": "Consumer Services",
    "dateListed": "2013-10-16",
    "marketCap": 1247873598,
    "xid": "68502887",
    "priceChangeFiveDayPercent": -0.5190311418685164,
    "isRecentListing": false,
    "priceAsk": 6.05,
    "priceBid": 5.55,
    "priceChange": 0.040000000000000036,
    "priceChangePercent": 0.7005253940455348,
    "priceLast": 5.75,
    "sector": "Industrials",
    "industryGroup": "Transportation",
    "securityType": 1,
    "volume": 133797,
    "statusCode": "",
    "isin": "AU0000186678",
    "priceClose": 5.71,
    "priceDayHigh": 5.83,
    "priceDayLow": 5.72,
    "priceFiftyTwoWeekHigh": 8.07,
    "priceFiftyTwoWeekLow": 4.32,
    "volumeAverage": 573278.043956,
    "dateExDate": "2022-09-02",
    "datePayDate": "2022-10-05",
    "dateRecordDate": "2022-09-05",
    "dividend": 0.095,
    "dividendType": "F",
    "frankingPercent": 100,
    "cashFlow": 59.301,
    "earningsPerShare": 0.24148,
    "freeCashFlowYield": 0.12110701500273702,
    "priceEarningsRatio": 23.8115,
    "priceToCash": 8.25716,
    "foreignExempt": false,
    "shareDescription": "Ordinary Fully Paid",
    "numOfShares": 218541786,
    "yieldAnnual": 2.869565217391304,
    "incomeStatement": [
      {
        "revenue": 1324808000,
        "netIncome": 52910000,
        "period": "2022A",
        "fPeriodEndDate": 44742,
        "curCode": "AUD"
      },
      {
        "revenue": 1173302000,
        "netIncome": 37798000,
        "period": "2021A",
        "fPeriodEndDate": 44377,
        "curCode": "AUD"
      },
      {
        "revenue": 624130000,
        "netIncome": -13572000,
        "period": "2020A",
        "fPeriodEndDate": 44012,
        "curCode": "AUD"
      },
      {
        "revenue": 248817000,
        "netIncome": 21543000,
        "period": "2019A",
        "fPeriodEndDate": 43646,
        "curCode": "AUD"
      }
    ]
  },
  {
    "symbol": "KED",
    "displayName": "KEYPATH EDUCATION INTERNATIONAL INC.",
    "industry": "Consumer Services",
    "dateListed": "2021-06-02",
    "marketCap": 132384806,
    "xid": "660038965",
    "priceChangeFiveDayPercent": 0,
    "isRecentListing": false,
    "priceAsk": 1,
    "priceBid": 0.62,
    "priceChange": 0,
    "priceChangePercent": 0,
    "priceLast": 0.62,
    "sector": "Consumer Discretionary",
    "industryGroup": "Consumer Services",
    "securityType": 1,
    "volume": 0,
    "statusCode": "",
    "isin": "AU0000152928",
    "priceClose": 0.62,
    "priceFiftyTwoWeekHigh": 2.86,
    "priceFiftyTwoWeekLow": 0.62,
    "volumeAverage": 13892.474576,
    "cashFlow": -9.70049,
    "earningsPerShare": -0.18914,
    "freeCashFlowYield": -0.0000100000010000001,
    "priceEarningsRatio": -99999.99,
    "priceToCash": -99999.99,
    "foreignExempt": false,
    "shareDescription": "Cdi 1:1 Us Person Prohibited Excluding Qib",
    "numOfShares": 213523881,
    "yieldAnnual": 0,
    "incomeStatement": [
      {
        "revenue": 118399000,
        "netIncome": -26695000,
        "period": "2022A",
        "fPeriodEndDate": 44742,
        "curCode": "USD"
      },
      {
        "revenue": 98092000,
        "netIncome": -78734000,
        "period": "2021A",
        "fPeriodEndDate": 44377,
        "curCode": "USD"
      },
      {
        "revenue": 55484000,
        "netIncome": -11398000,
        "period": "2020A",
        "fPeriodEndDate": 44012,
        "curCode": "USD"
      },
      {
        "revenue": 37242000,
        "netIncome": -19691000,
        "period": "2019A",
        "fPeriodEndDate": 43646,
        "curCode": "USD"
      }
    ]
  },
  {
    "symbol": "KME",
    "displayName": "KIP MCGRATH EDUCATION CENTRES LIMITED",
    "industry": "Consumer Services",
    "dateListed": "2003-08-15",
    "marketCap": 46940882,
    "xid": "178373",
    "priceChangeFiveDayPercent": 3.105590062111804,
    "isRecentListing": false,
    "priceAsk": 0.84,
    "priceBid": 0.8300000000000001,
    "priceChange": 0,
    "priceChangePercent": 0,
    "priceLast": 0.8300000000000001,
    "sector": "Consumer Discretionary",
    "industryGroup": "Consumer Services",
    "securityType": 1,
    "volume": 3778,
    "statusCode": "",
    "isin": "AU000000KME9",
    "priceClose": 0.8300000000000001,
    "priceDayHigh": 0.8300000000000001,
    "priceDayLow": 0.8300000000000001,
    "priceFiftyTwoWeekHigh": 1.2425,
    "priceFiftyTwoWeekLow": 0.75,
    "volumeAverage": 24058.865854,
    "dateExDate": "2022-09-07",
    "datePayDate": "2022-09-22",
    "dateRecordDate": "2022-09-08",
    "dividend": 0.01,
    "dividendType": "F",
    "frankingPercent": 100,
    "cashFlow": -0.81,
    "earningsPerShare": 0.03409,
    "freeCashFlowYield": 0.11503826172585002,
    "priceEarningsRatio": 24.34732,
    "priceToCash": 8.69276,
    "foreignExempt": false,
    "shareDescription": "Ordinary Fully Paid",
    "numOfShares": 56555280,
    "yieldAnnual": 2.4096385542168672,
    "incomeStatement": [
      {
        "revenue": 24648000,
        "netIncome": 1878000,
        "period": "2022A",
        "fPeriodEndDate": 44742,
        "curCode": "AUD"
      },
      {
        "revenue": 19278000,
        "netIncome": 1733000,
        "period": "2021A",
        "fPeriodEndDate": 44377,
        "curCode": "AUD"
      },
      {
        "revenue": 17123000,
        "netIncome": 1573000,
        "period": "2020A",
        "fPeriodEndDate": 44012,
        "curCode": "AUD"
      },
      {
        "revenue": 16263000,
        "netIncome": 2652000,
        "period": "2019A",
        "fPeriodEndDate": 43646,
        "curCode": "AUD"
      }
    ]
  },
  {
    "symbol": "MMM",
    "displayName": "MARLEY SPOON AG",
    "industry": "Consumer Services",
    "dateListed": "2018-07-02",
    "marketCap": 51136765,
    "xid": "739228644",
    "priceChangeFiveDayPercent": 0,
    "isRecentListing": false,
    "priceAsk": 0.14,
    "priceBid": 0.13,
    "priceChange": 0,
    "priceChangePercent": 0,
    "priceLast": 0.13,
    "sector": "Consumer Discretionary",
    "industryGroup": "Retailing",
    "securityType": 1,
    "volume": 97877,
    "statusCode": "RE",
    "isin": "AU0000013070",
    "priceClose": 0.13,
    "priceDayHigh": 0.14,
    "priceDayLow": 0.13,
    "priceFiftyTwoWeekHigh": 1,
    "priceFiftyTwoWeekLow": 0.13,
    "volumeAverage": 466997.977528,
    "cashFlow": -59.96442,
    "earningsPerShare": -0.15044,
    "freeCashFlowYield": -0.0000100000010000001,
    "priceEarningsRatio": -99999.99,
    "priceToCash": -99999.99,
    "foreignExempt": false,
    "shareDescription": "Chess Depositary Interests 10:1",
    "numOfShares": 393359730,
    "yieldAnnual": 0,
    "incomeStatement": [
      {
        "revenue": 322393000,
        "netIncome": -46207000,
        "period": "2021A",
        "fPeriodEndDate": 44561,
        "curCode": "EUR"
      },
      {
        "revenue": 254033000,
        "netIncome": -86239000,
        "period": "2020A",
        "fPeriodEndDate": 44196,
        "curCode": "EUR"
      },
      {
        "revenue": 129558000,
        "netIncome": -34548000,
        "period": "2019A",
        "fPeriodEndDate": 43830,
        "curCode": "EUR"
      },
      {
        "revenue": 91988000,
        "netIncome": -40985000,
        "period": "2018A",
        "fPeriodEndDate": 43465,
        "curCode": "EUR"
      }
    ]
  },
  {
    "symbol": "MFD",
    "displayName": "MAYFIELD CHILDCARE LIMITED",
    "industry": "Consumer Services",
    "dateListed": "2016-11-30",
    "marketCap": 90131533,
    "xid": "372813491",
    "priceChangeFiveDayPercent": 0.724637681159437,
    "isRecentListing": false,
    "priceAsk": 1.385,
    "priceBid": 1.3800000000000001,
    "priceChange": 0.010000000000000009,
    "priceChangePercent": 0.7246376811594208,
    "priceLast": 1.3900000000000001,
    "sector": "Consumer Discretionary",
    "industryGroup": "Consumer Services",
    "securityType": 1,
    "volume": 6850,
    "statusCode": "",
    "isin": "AU000000MFD1",
    "priceClose": 1.3800000000000001,
    "priceDayHigh": 1.3900000000000001,
    "priceDayLow": 1.3800000000000001,
    "priceFiftyTwoWeekHigh": 1.49,
    "priceFiftyTwoWeekLow": 0.96,
    "volumeAverage": 86029.289157,
    "dateExDate": "2022-08-25",
    "datePayDate": "2022-09-23",
    "dateRecordDate": "2022-08-26",
    "dividend": 0.0276,
    "dividendType": "I",
    "frankingPercent": 100,
    "cashFlow": 11.56088,
    "earningsPerShare": 0.07457,
    "freeCashFlowYield": 0.12635052921919165,
    "priceEarningsRatio": 18.6402,
    "priceToCash": 7.91449,
    "foreignExempt": false,
    "shareDescription": "Ordinary Fully Paid",
    "numOfShares": 65312705,
    "yieldAnnual": 0,
    "incomeStatement": [
      {
        "revenue": 40062380,
        "netIncome": 2571330,
        "period": "2021A",
        "fPeriodEndDate": 44561,
        "curCode": "AUD"
      },
      {
        "revenue": 37536190,
        "netIncome": 3738720,
        "period": "2020A",
        "fPeriodEndDate": 44196,
        "curCode": "AUD"
      },
      {
        "revenue": 35865870,
        "netIncome": 3346510,
        "period": "2019A",
        "fPeriodEndDate": 43830,
        "curCode": "AUD"
      },
      {
        "revenue": 31488840,
        "netIncome": 4274740,
        "period": "2018A",
        "fPeriodEndDate": 43465,
        "curCode": "AUD"
      }
    ]
  },
  {
    "symbol": "MCL",
    "displayName": "MIGHTY CRAFT LIMITED",
    "industry": "Consumer Services",
    "dateListed": "2019-12-17",
    "marketCap": 58390563,
    "xid": "566872702",
    "priceChangeFiveDayPercent": 2.85714285714286,
    "isRecentListing": false,
    "priceAsk": 0.19,
    "priceBid": 0.17500000000000002,
    "priceChange": 0,
    "priceChangePercent": 0,
    "priceLast": 0.18,
    "sector": "Consumer Discretionary",
    "industryGroup": "Consumer Services",
    "securityType": 1,
    "volume": 585,
    "statusCode": "",
    "isin": "AU0000115610",
    "priceClose": 0.18,
    "priceDayHigh": 0.18,
    "priceDayLow": 0.18,
    "priceFiftyTwoWeekHigh": 0.395,
    "priceFiftyTwoWeekLow": 0.125,
    "volumeAverage": 186335.285714,
    "cashFlow": -14.686,
    "earningsPerShare": -0.05461,
    "freeCashFlowYield": -0.0000100000010000001,
    "priceEarningsRatio": -99999.99,
    "priceToCash": -99999.99,
    "foreignExempt": false,
    "shareDescription": "Ordinary Fully Paid",
    "numOfShares": 324392015,
    "yieldAnnual": 0,
    "incomeStatement": [
      {
        "revenue": 62598000,
        "netIncome": -20644000,
        "period": "2022A",
        "fPeriodEndDate": 44742,
        "curCode": "AUD"
      },
      {
        "revenue": 29307960,
        "netIncome": -15001100,
        "period": "2021A",
        "fPeriodEndDate": 44377,
        "curCode": "AUD"
      },
      {
        "revenue": 9280040,
        "netIncome": -8516680,
        "period": "2020A",
        "fPeriodEndDate": 44012,
        "curCode": "AUD"
      },
      {
        "revenue": 4002960,
        "netIncome": -1526160,
        "period": "2019A",
        "fPeriodEndDate": 43646,
        "curCode": "AUD"
      }
    ]
  },
  {
    "symbol": "NXD",
    "displayName": "NEXTED GROUP LIMITED",
    "industry": "Consumer Services",
    "dateListed": "2009-08-24",
    "marketCap": 248742937,
    "xid": "19876426",
    "priceChangeFiveDayPercent": -2.5641025641025474,
    "isRecentListing": false,
    "priceAsk": 1.18,
    "priceBid": 1.1300000000000001,
    "priceChange": 0.0050000000000001155,
    "priceChangePercent": 0.4405286343612437,
    "priceLast": 1.1400000000000001,
    "sector": "Consumer Discretionary",
    "industryGroup": "Consumer Services",
    "securityType": 1,
    "volume": 94374,
    "statusCode": "RE",
    "isin": "AU0000258865",
    "priceClose": 1.135,
    "priceDayHigh": 1.16,
    "priceDayLow": 1.125,
    "priceFiftyTwoWeekHigh": 1.4,
    "priceFiftyTwoWeekLow": 0.465,
    "volumeAverage": 412513.569231,
    "cashFlow": 8.273,
    "earningsPerShare": -0.04846,
    "freeCashFlowYield": -0.0000100000010000001,
    "priceEarningsRatio": -99999.99,
    "priceToCash": -99999.99,
    "foreignExempt": false,
    "shareDescription": "Ordinary Fully Paid",
    "numOfShares": 219156773,
    "yieldAnnual": 0,
    "incomeStatement": [
      {
        "revenue": 48310000,
        "netIncome": -8695000,
        "period": "2022A",
        "fPeriodEndDate": 44742,
        "curCode": "AUD"
      },
      {
        "revenue": 16291100,
        "netIncome": 308100,
        "period": "2021A",
        "fPeriodEndDate": 44377,
        "curCode": "AUD"
      },
      {
        "revenue": 10807660,
        "netIncome": -2640240,
        "period": "2020A",
        "fPeriodEndDate": 44012,
        "curCode": "AUD"
      },
      {
        "revenue": 8545270,
        "netIncome": -13495190,
        "period": "2019A",
        "fPeriodEndDate": 43646,
        "curCode": "AUD"
      }
    ]
  },
  {
    "symbol": "OLI",
    "displayName": "OLIVER'S REAL FOOD LIMITED",
    "industry": "Consumer Services",
    "dateListed": "2017-06-21",
    "marketCap": -1,
    "xid": "411920751",
    "priceChangeFiveDayPercent": 0,
    "isRecentListing": false,
    "priceChange": 0,
    "priceChangePercent": 0,
    "priceLast": 0.059000000000000004,
    "sector": "Consumer Discretionary",
    "industryGroup": "Consumer Services",
    "securityType": 1,
    "volume": 0,
    "statusCode": "",
    "isin": "AU000000OLI4",
    "priceClose": 0.059000000000000004,
    "priceFiftyTwoWeekHigh": 0.065,
    "priceFiftyTwoWeekLow": 0.059000000000000004,
    "cashFlow": -2.21806,
    "earningsPerShare": -0.03762,
    "freeCashFlowYield": -0.0000100000010000001,
    "priceEarningsRatio": -99999.99,
    "priceToCash": -99999.99,
    "foreignExempt": false,
    "shareDescription": "Ordinary Fully Paid",
    "numOfShares": 360731917,
    "yieldAnnual": 0,
    "incomeStatement": [
      {
        "revenue": 19486470,
        "netIncome": -11669880,
        "period": "2022A",
        "fPeriodEndDate": 44742,
        "curCode": "AUD"
      },
      {
        "revenue": 28180330,
        "netIncome": -9284870,
        "period": "2021A",
        "fPeriodEndDate": 44377,
        "curCode": "AUD"
      },
      {
        "revenue": 28539650,
        "netIncome": -17506370,
        "period": "2020A",
        "fPeriodEndDate": 44012,
        "curCode": "AUD"
      },
      {
        "revenue": 34973120,
        "netIncome": -15661500,
        "period": "2019A",
        "fPeriodEndDate": 43646,
        "curCode": "AUD"
      }
    ]
  },
  {
    "symbol": "PBH",
    "displayName": "POINTSBET HOLDINGS LIMITED",
    "industry": "Consumer Services",
    "dateListed": "2019-06-12",
    "marketCap": 441706547,
    "xid": "538365188",
    "priceChangeFiveDayPercent": 10.40892193308551,
    "isRecentListing": false,
    "priceAsk": 1.5250000000000001,
    "priceBid": 1.48,
    "priceChange": 0.040000000000000036,
    "priceChangePercent": 2.7681660899654004,
    "priceLast": 1.485,
    "sector": "Consumer Discretionary",
    "industryGroup": "Consumer Services",
    "securityType": 1,
    "volume": 1235978,
    "statusCode": "",
    "isin": "AU0000047797",
    "priceClose": 1.445,
    "priceDayHigh": 1.545,
    "priceDayLow": 1.45,
    "priceFiftyTwoWeekHigh": 7.23,
    "priceFiftyTwoWeekLow": 1.215,
    "volumeAverage": 1839743.945055,
    "cashFlow": -286.102,
    "earningsPerShare": -1.05162,
    "freeCashFlowYield": -0.0000100000010000001,
    "priceEarningsRatio": -99999.99,
    "priceToCash": -99999.99,
    "foreignExempt": false,
    "shareDescription": "Ordinary Fully Paid",
    "numOfShares": 305679271,
    "yieldAnnual": 0,
    "incomeStatement": [
      {
        "revenue": 296483000,
        "netIncome": -267689000,
        "period": "2022A",
        "fPeriodEndDate": 44742,
        "curCode": "AUD"
      },
      {
        "revenue": 194658000,
        "netIncome": -187733000,
        "period": "2021A",
        "fPeriodEndDate": 44377,
        "curCode": "AUD"
      },
      {
        "revenue": 75173420,
        "netIncome": -41463390,
        "period": "2020A",
        "fPeriodEndDate": 44012,
        "curCode": "AUD"
      },
      {
        "revenue": 25615270,
        "netIncome": -41885150,
        "period": "2019A",
        "fPeriodEndDate": 43646,
        "curCode": "AUD"
      }
    ]
  },
  {
    "symbol": "PFP",
    "displayName": "PROPEL FUNERAL PARTNERS LIMITED",
    "industry": "Consumer Services",
    "dateListed": "2017-11-23",
    "marketCap": 516664756,
    "xid": "440268233",
    "priceChangeFiveDayPercent": -1.3667425968109252,
    "isRecentListing": false,
    "priceAsk": 4.33,
    "priceBid": 4.25,
    "priceChange": -0.04999999999999982,
    "priceChangePercent": -1.1415525114155212,
    "priceLast": 4.33,
    "sector": "Consumer Discretionary",
    "industryGroup": "Consumer Services",
    "securityType": 1,
    "volume": 7174,
    "statusCode": "",
    "isin": "AU000000PFP8",
    "priceClose": 4.38,
    "priceDayHigh": 4.37,
    "priceDayLow": 4.29,
    "priceFiftyTwoWeekHigh": 5.2,
    "priceFiftyTwoWeekLow": 4.1,
    "volumeAverage": 61707.043956,
    "dateExDate": "2022-08-31",
    "datePayDate": "2022-10-04",
    "dateRecordDate": "2022-09-01",
    "dividend": 0.0625,
    "dividendType": "F",
    "frankingPercent": 100,
    "cashFlow": -1.402,
    "earningsPerShare": -0.0105,
    "freeCashFlowYield": 0.019605817202810613,
    "priceEarningsRatio": -99999.99,
    "priceToCash": 51.00527,
    "foreignExempt": false,
    "shareDescription": "Ordinary Fully Paid",
    "numOfShares": 117959990,
    "yieldAnnual": 0,
    "incomeStatement": [
      {
        "revenue": 145331000,
        "netIncome": -318000,
        "period": "2022A",
        "fPeriodEndDate": 44742,
        "curCode": "AUD"
      },
      {
        "revenue": 120537000,
        "netIncome": 14443000,
        "period": "2021A",
        "fPeriodEndDate": 44377,
        "curCode": "AUD"
      },
      {
        "revenue": 110993000,
        "netIncome": 10624000,
        "period": "2020A",
        "fPeriodEndDate": 44012,
        "curCode": "AUD"
      },
      {
        "revenue": 95439000,
        "netIncome": 12340000,
        "period": "2019A",
        "fPeriodEndDate": 43646,
        "curCode": "AUD"
      }
    ]
  },
  {
    "symbol": "RCT",
    "displayName": "REEF CASINO TRUST",
    "industry": "Consumer Services",
    "dateListed": "1994-02-11",
    "marketCap": 164343419,
    "xid": "239963",
    "priceChangeFiveDayPercent": -10.059171597633132,
    "isRecentListing": false,
    "priceAsk": 3.15,
    "priceBid": 3.06,
    "priceChange": -0.26000000000000023,
    "priceChangePercent": -7.878787878787884,
    "priceLast": 3.04,
    "sector": "Consumer Discretionary",
    "industryGroup": "Consumer Services",
    "securityType": 6,
    "volume": 7997,
    "statusCode": "XD",
    "isin": "AU000000RCT3",
    "priceClose": 3.3000000000000003,
    "priceDayHigh": 3.0500000000000003,
    "priceDayLow": 3.04,
    "priceFiftyTwoWeekHigh": 3.48,
    "priceFiftyTwoWeekLow": 2.75,
    "volumeAverage": 4936.1625,
    "dateExDate": "2022-12-29",
    "datePayDate": "2023-03-08",
    "dateRecordDate": "2022-12-30",
    "dividend": 0.2237,
    "dividendType": "F",
    "frankingPercent": 0,
    "cashFlow": 0.556,
    "earningsPerShare": 0.30453,
    "freeCashFlowYield": 0.08216805338951437,
    "priceEarningsRatio": 9.9826,
    "priceToCash": 12.17018,
    "foreignExempt": false,
    "shareDescription": "Units Fully Paid",
    "numOfShares": 49801036,
    "yieldAnnual": 11.694078947368421,
    "incomeStatement": [
      {
        "revenue": 26874000,
        "netIncome": 7361000,
        "period": "2021A",
        "fPeriodEndDate": 44561,
        "curCode": "AUD"
      },
      {
        "revenue": 15663000,
        "netIncome": -209000,
        "period": "2020A",
        "fPeriodEndDate": 44196,
        "curCode": "AUD"
      },
      {
        "revenue": 19060000,
        "netIncome": 3335000,
        "period": "2019A",
        "fPeriodEndDate": 43830,
        "curCode": "AUD"
      },
      {
        "revenue": 21417000,
        "netIncome": 5050000,
        "period": "2018A",
        "fPeriodEndDate": 43465,
        "curCode": "AUD"
      }
    ]
  },
  {
    "symbol": "RBD",
    "displayName": "RESTAURANT BRANDS NEW ZEALAND LIMITED",
    "industry": "Consumer Services",
    "dateListed": "2017-09-28",
    "marketCap": 736075286,
    "xid": "428980596",
    "priceChangeFiveDayPercent": -3.2786885245901525,
    "isRecentListing": false,
    "priceAsk": 7.07,
    "priceBid": 5.91,
    "priceChangePercent": 0,
    "priceLast": 5.9,
    "sector": "Consumer Discretionary",
    "industryGroup": "Consumer Services",
    "securityType": 1,
    "volume": 0,
    "statusCode": "",
    "isin": "NZRBDE0001S1",
    "priceClose": 5.9,
    "priceFiftyTwoWeekHigh": 12.53,
    "priceFiftyTwoWeekLow": 5.9,
    "volumeAverage": 784.742857,
    "dateExDate": "2022-04-07",
    "datePayDate": "2022-04-22",
    "dateRecordDate": "2022-04-08",
    "dividend": 0.297,
    "dividendType": "F",
    "frankingPercent": 0,
    "cashFlow": -15.593,
    "earningsPerShare": 0.26175,
    "freeCashFlowYield": 0.17109078932735658,
    "priceEarningsRatio": 21.96753,
    "priceToCash": 5.84485,
    "foreignExempt": true,
    "shareDescription": "Ordinary Fully Paid Foreign Exempt Nzx",
    "numOfShares": 124758523,
    "yieldAnnual": 0,
    "incomeStatement": [
      {
        "revenue": 1114441000,
        "netIncome": 51881000,
        "period": "2021A",
        "fPeriodEndDate": 44561,
        "curCode": "NZD"
      },
      {
        "revenue": 924728000,
        "netIncome": 30644000,
        "period": "2020A",
        "fPeriodEndDate": 44196,
        "curCode": "NZD"
      },
      {
        "revenue": 733666000,
        "netIncome": 30091000,
        "period": "2019A",
        "fPeriodEndDate": 43830,
        "curCode": "NZD"
      },
      {
        "revenue": 766289000,
        "netIncome": 35466000,
        "period": "2018A",
        "fPeriodEndDate": 43157,
        "curCode": "NZD"
      }
    ]
  },
  {
    "symbol": "RFG",
    "displayName": "RETAIL FOOD GROUP LIMITED",
    "industry": "Consumer Services",
    "dateListed": "2006-06-22",
    "marketCap": 166179277,
    "xid": "4888444",
    "priceChangeFiveDayPercent": 5.263157894736847,
    "isRecentListing": false,
    "priceAsk": 0.08,
    "priceBid": 0.079,
    "priceChange": 0.0020000000000000018,
    "priceChangePercent": 2.5641025641025665,
    "priceLast": 0.08,
    "sector": "Consumer Discretionary",
    "industryGroup": "Consumer Services",
    "securityType": 1,
    "volume": 1754272,
    "statusCode": "",
    "isin": "AU000000RFG3",
    "priceClose": 0.078,
    "priceDayHigh": 0.08,
    "priceDayLow": 0.078,
    "priceFiftyTwoWeekHigh": 0.083,
    "priceFiftyTwoWeekLow": 0.038,
    "volumeAverage": 1486091.395604,
    "dateExDate": "2017-09-11",
    "datePayDate": "2017-10-17",
    "dateRecordDate": "2017-09-12",
    "dividend": 0.15,
    "dividendType": "F",
    "frankingPercent": 100,
    "cashFlow": 12.319,
    "earningsPerShare": 0.00229,
    "freeCashFlowYield": 0.07994001301423412,
    "priceEarningsRatio": 34.9345,
    "priceToCash": 12.50938,
    "foreignExempt": false,
    "shareDescription": "Ordinary Fully Paid",
    "numOfShares": 2130503555,
    "yieldAnnual": 0,
    "incomeStatement": [
      {
        "revenue": 111843000,
        "netIncome": 5259000,
        "period": "2022A",
        "fPeriodEndDate": 44742,
        "curCode": "AUD"
      },
      {
        "revenue": 117586000,
        "netIncome": 1461000,
        "period": "2021A",
        "fPeriodEndDate": 44377,
        "curCode": "AUD"
      },
      {
        "revenue": 137219000,
        "netIncome": -3990000,
        "period": "2020A",
        "fPeriodEndDate": 44012,
        "curCode": "AUD"
      },
      {
        "revenue": 271359000,
        "netIncome": -142537000,
        "period": "2019A",
        "fPeriodEndDate": 43646,
        "curCode": "AUD"
      }
    ]
  },
  {
    "symbol": "RTE",
    "displayName": "RETECH TECHNOLOGY CO. LIMITED",
    "industry": "Consumer Services",
    "dateListed": "2017-06-22",
    "marketCap": -1,
    "xid": "402170356",
    "priceChangeFiveDayPercent": 0,
    "isRecentListing": false,
    "priceChange": 0,
    "priceChangePercent": 0,
    "priceLast": 0.14,
    "sector": "Consumer Discretionary",
    "industryGroup": "Consumer Services",
    "securityType": 1,
    "volume": 0,
    "statusCode": "",
    "isin": "AU000000RTE9",
    "priceClose": 0.14,
    "priceFiftyTwoWeekHigh": 0.28,
    "priceFiftyTwoWeekLow": 0.14,
    "dateExDate": "2019-11-14",
    "datePayDate": "2019-11-27",
    "dateRecordDate": "2019-11-15",
    "dividend": 0.005,
    "dividendType": "I",
    "frankingPercent": 0,
    "cashFlow": -5.17753,
    "earningsPerShare": 0.00462,
    "freeCashFlowYield": 0.01777873229816072,
    "priceEarningsRatio": 30.33454,
    "priceToCash": 56.24698,
    "foreignExempt": false,
    "shareDescription": "Chess Depositary Interests 1:1",
    "numOfShares": 232912633,
    "yieldAnnual": 0,
    "incomeStatement": [
      {
        "revenue": 187344680,
        "netIncome": 5072370,
        "period": "2021A",
        "fPeriodEndDate": 44561,
        "curCode": "CNY"
      },
      {
        "revenue": 195755510,
        "netIncome": 54404060,
        "period": "2020A",
        "fPeriodEndDate": 44196,
        "curCode": "CNY"
      },
      {
        "revenue": 167740590,
        "netIncome": 53759640,
        "period": "2019A",
        "fPeriodEndDate": 43830,
        "curCode": "CNY"
      },
      {
        "revenue": 130501400,
        "netIncome": 49233150,
        "period": "2018A",
        "fPeriodEndDate": 43465,
        "curCode": "CNY"
      }
    ]
  },
  {
    "symbol": "SCT",
    "displayName": "SCOUT SECURITY LIMITED",
    "industry": "Consumer Services",
    "dateListed": "2017-08-25",
    "marketCap": 6681445,
    "xid": "403817190",
    "priceChangeFiveDayPercent": 15.384615384615387,
    "isRecentListing": false,
    "priceAsk": 0.03,
    "priceBid": 0.029,
    "priceChange": 0.0009999999999999974,
    "priceChangePercent": 3.4482758620689564,
    "priceLast": 0.03,
    "sector": "Consumer Discretionary",
    "industryGroup": "Consumer Services",
    "securityType": 1,
    "volume": 205000,
    "statusCode": "",
    "isin": "AU000000SCT1",
    "priceClose": 0.029,
    "priceDayHigh": 0.03,
    "priceDayLow": 0.029,
    "priceFiftyTwoWeekHigh": 0.051,
    "priceFiftyTwoWeekLow": 0.02021,
    "volumeAverage": 200246.200432,
    "cashFlow": -3.75595,
    "earningsPerShare": -0.0209,
    "freeCashFlowYield": -0.0000100000010000001,
    "priceEarningsRatio": -99999.99,
    "priceToCash": -99999.99,
    "foreignExempt": false,
    "shareDescription": "Ordinary Fully Paid",
    "numOfShares": 230394648,
    "yieldAnnual": 0,
    "incomeStatement": [
      {
        "revenue": 4323350,
        "netIncome": -3288920,
        "period": "2022A",
        "fPeriodEndDate": 44742,
        "curCode": "AUD"
      },
      {
        "revenue": 1671350,
        "netIncome": -3943800,
        "period": "2021A",
        "fPeriodEndDate": 44377,
        "curCode": "AUD"
      },
      {
        "revenue": 3124850,
        "netIncome": -1593250,
        "period": "2020A",
        "fPeriodEndDate": 44012,
        "curCode": "AUD"
      },
      {
        "revenue": 2908070,
        "netIncome": -3634170,
        "period": "2019A",
        "fPeriodEndDate": 43646,
        "curCode": "AUD"
      }
    ]
  },
  {
    "symbol": "SHJ",
    "displayName": "SHINE JUSTICE LTD",
    "industry": "Consumer Services",
    "dateListed": "2013-05-15",
    "marketCap": 163732412,
    "xid": "56845837",
    "priceChangeFiveDayPercent": -1.5544041450777102,
    "isRecentListing": false,
    "priceAsk": 1,
    "priceBid": 0.9400000000000001,
    "priceChange": 0.0050000000000000044,
    "priceChangePercent": 0.5291005291005295,
    "priceLast": 0.9500000000000001,
    "sector": "Consumer Discretionary",
    "industryGroup": "Consumer Services",
    "securityType": 1,
    "volume": 97464,
    "statusCode": "",
    "isin": "AU000000SHJ1",
    "priceClose": 0.9450000000000001,
    "priceDayHigh": 0.96,
    "priceDayLow": 0.9450000000000001,
    "priceFiftyTwoWeekHigh": 1.44,
    "priceFiftyTwoWeekLow": 0.82,
    "volumeAverage": 71218.130952,
    "dateExDate": "2022-09-21",
    "datePayDate": "2022-10-07",
    "dateRecordDate": "2022-09-23",
    "dividend": 0.035,
    "dividendType": "F",
    "frankingPercent": 0,
    "cashFlow": -5.073,
    "earningsPerShare": 0.17568,
    "freeCashFlowYield": 0.27048812286652496,
    "priceEarningsRatio": 5.40756,
    "priceToCash": 3.69702,
    "foreignExempt": false,
    "shareDescription": "Ordinary Fully Paid",
    "numOfShares": 173261812,
    "yieldAnnual": 6.315789473684211,
    "incomeStatement": [
      {
        "revenue": 215132000,
        "netIncome": 31143000,
        "period": "2022A",
        "fPeriodEndDate": 44742,
        "curCode": "AUD"
      },
      {
        "revenue": 187210000,
        "netIncome": 25556000,
        "period": "2021A",
        "fPeriodEndDate": 44377,
        "curCode": "AUD"
      },
      {
        "revenue": 183032000,
        "netIncome": 21476000,
        "period": "2020A",
        "fPeriodEndDate": 44012,
        "curCode": "AUD"
      },
      {
        "revenue": 177903000,
        "netIncome": 13953000,
        "period": "2019A",
        "fPeriodEndDate": 43646,
        "curCode": "AUD"
      }
    ]
  },
  {
    "symbol": "SIT",
    "displayName": "SITE GROUP INTERNATIONAL LIMITED",
    "industry": "Consumer Services",
    "dateListed": "1987-08-21",
    "marketCap": 4204981,
    "xid": "254808",
    "priceChangeFiveDayPercent": 0,
    "isRecentListing": false,
    "priceAsk": 0.004,
    "priceBid": 0.002,
    "priceChange": 0,
    "priceChangePercent": 0,
    "priceLast": 0.004,
    "sector": "Consumer Discretionary",
    "industryGroup": "Consumer Services",
    "securityType": 1,
    "volume": 0,
    "statusCode": "",
    "isin": "AU000000SIT8",
    "priceClose": 0.004,
    "priceFiftyTwoWeekHigh": 0.007,
    "priceFiftyTwoWeekLow": 0.002,
    "volumeAverage": 966314.52381,
    "cashFlow": -1.72237,
    "earningsPerShare": -0.00772,
    "freeCashFlowYield": -0.0000100000010000001,
    "priceEarningsRatio": -99999.99,
    "priceToCash": -99999.99,
    "foreignExempt": false,
    "shareDescription": "Ordinary Fully Paid",
    "numOfShares": 1051245127,
    "yieldAnnual": 0,
    "incomeStatement": [
      {
        "revenue": 7141830,
        "netIncome": -7254840,
        "period": "2022A",
        "fPeriodEndDate": 44742,
        "curCode": "AUD"
      },
      {
        "revenue": 7362540,
        "netIncome": -7276210,
        "period": "2021A",
        "fPeriodEndDate": 44377,
        "curCode": "AUD"
      },
      {
        "revenue": 15320720,
        "netIncome": -10264690,
        "period": "2020A",
        "fPeriodEndDate": 44012,
        "curCode": "AUD"
      },
      {
        "revenue": 30913290,
        "netIncome": -4626470,
        "period": "2019A",
        "fPeriodEndDate": 43646,
        "curCode": "AUD"
      }
    ]
  },
  {
    "symbol": "SDR",
    "displayName": "SITEMINDER LIMITED",
    "industry": "Consumer Services",
    "dateListed": "2021-11-08",
    "marketCap": 824564616,
    "xid": "687232087",
    "priceChangeFiveDayPercent": -0.6535947712418306,
    "isRecentListing": false,
    "priceAsk": 3.08,
    "priceBid": 3,
    "priceChange": 0.040000000000000036,
    "priceChangePercent": 1.3333333333333346,
    "priceLast": 3.04,
    "sector": "Information Technology",
    "industryGroup": "Software & Services",
    "securityType": 1,
    "volume": 130893,
    "statusCode": "",
    "isin": "AU0000183543",
    "priceClose": 3,
    "priceDayHigh": 3.08,
    "priceDayLow": 3,
    "priceFiftyTwoWeekHigh": 7.03,
    "priceFiftyTwoWeekLow": 2.68,
    "volumeAverage": 435533.417582,
    "cashFlow": -99999.99,
    "earningsPerShare": -99999.99,
    "freeCashFlowYield": -0.0000100000010000001,
    "priceEarningsRatio": -99999.99,
    "priceToCash": -99999.99,
    "foreignExempt": false,
    "shareDescription": "Ordinary Fully Paid",
    "numOfShares": 274854872,
    "yieldAnnual": 0,
    "incomeStatement": [
      {
        "revenue": 100761000,
        "netIncome": -121770000,
        "period": "2021A",
        "fPeriodEndDate": 44377,
        "curCode": "AUD"
      },
      {
        "revenue": 112196000,
        "netIncome": -4899000,
        "period": "2020A",
        "fPeriodEndDate": 44012,
        "curCode": "AUD"
      },
      {
        "revenue": 96862000,
        "netIncome": -147126000,
        "period": "2019A",
        "fPeriodEndDate": 43646,
        "curCode": "AUD"
      }
    ]
  },
  {
    "symbol": "SKC",
    "displayName": "SKYCITY ENTERTAINMENT GROUP LIMITED",
    "industry": "Consumer Services",
    "dateListed": "1999-03-29",
    "marketCap": 1695257616,
    "xid": "254471",
    "priceChangeFiveDayPercent": -1.739130434782591,
    "isRecentListing": false,
    "priceAsk": 2.32,
    "priceBid": 2.22,
    "priceChange": 0.03000000000000025,
    "priceChangePercent": 1.345291479820639,
    "priceLast": 2.2600000000000002,
    "sector": "Consumer Discretionary",
    "industryGroup": "Consumer Services",
    "securityType": 1,
    "volume": 126087,
    "statusCode": "",
    "isin": "NZSKCE0001S2",
    "priceClose": 2.23,
    "priceDayHigh": 2.2600000000000002,
    "priceDayLow": 2.22,
    "priceFiftyTwoWeekHigh": 2.98,
    "priceFiftyTwoWeekLow": 2.22,
    "volumeAverage": 310075.714286,
    "dateExDate": "2021-09-16",
    "datePayDate": "2021-09-24",
    "dateRecordDate": "2021-09-17",
    "dividend": 0.0677,
    "dividendType": "F",
    "frankingPercent": 0,
    "cashFlow": -99999.99,
    "earningsPerShare": -0.04484,
    "freeCashFlowYield": 0.03395412797310834,
    "priceEarningsRatio": -99999.99,
    "priceToCash": 29.4515,
    "foreignExempt": true,
    "shareDescription": "Ordinary Fully Paid Foreign Exempt Nzx",
    "numOfShares": 760205209,
    "yieldAnnual": 2.991150442477876,
    "incomeStatement": [
      {
        "revenue": 553543000,
        "netIncome": -33595000,
        "period": "2022A",
        "fPeriodEndDate": 44742,
        "curCode": "NZD"
      },
      {
        "revenue": 713216000,
        "netIncome": 155833000,
        "period": "2021A",
        "fPeriodEndDate": 44377,
        "curCode": "NZD"
      },
      {
        "revenue": 641653000,
        "netIncome": 235388000,
        "period": "2020A",
        "fPeriodEndDate": 44012,
        "curCode": "NZD"
      },
      {
        "revenue": 802265000,
        "netIncome": 144581000,
        "period": "2019A",
        "fPeriodEndDate": 43646,
        "curCode": "NZD"
      }
    ]
  },
  {
    "symbol": "SGH",
    "displayName": "SLATER & GORDON LIMITED",
    "industry": "Consumer Services",
    "dateListed": "2007-05-21",
    "marketCap": 76884969,
    "xid": "7334326",
    "priceChangeFiveDayPercent": 0.9259259259259267,
    "isRecentListing": false,
    "priceAsk": 0.545,
    "priceBid": 0.525,
    "priceChange": 0,
    "priceChangePercent": 0,
    "priceLast": 0.545,
    "sector": "Consumer Discretionary",
    "industryGroup": "Consumer Services",
    "securityType": 1,
    "volume": 0,
    "statusCode": "",
    "isin": "AU000000SGH7",
    "priceClose": 0.545,
    "priceFiftyTwoWeekHigh": 0.745,
    "priceFiftyTwoWeekLow": 0.505,
    "volumeAverage": 4279.578947,
    "dateExDate": "2015-09-18",
    "datePayDate": "2015-10-29",
    "dateRecordDate": "2015-09-22",
    "dividend": 0.055,
    "dividendType": "F",
    "frankingPercent": 40,
    "cashFlow": -15.332,
    "earningsPerShare": 0.01055,
    "freeCashFlowYield": 0.12392541177316198,
    "priceEarningsRatio": 51.65877,
    "priceToCash": 8.06937,
    "foreignExempt": false,
    "shareDescription": "Ordinary Fully Paid",
    "numOfShares": 141073337,
    "yieldAnnual": 0,
    "incomeStatement": [
      {
        "revenue": 182617000,
        "netIncome": 2156000,
        "period": "2022A",
        "fPeriodEndDate": 44742,
        "curCode": "AUD"
      },
      {
        "revenue": 203443000,
        "netIncome": 14470000,
        "period": "2021A",
        "fPeriodEndDate": 44377,
        "curCode": "AUD"
      },
      {
        "revenue": 178339000,
        "netIncome": -1185000,
        "period": "2020A",
        "fPeriodEndDate": 44012,
        "curCode": "AUD"
      },
      {
        "revenue": 160372000,
        "netIncome": 31260000,
        "period": "2019A",
        "fPeriodEndDate": 43646,
        "curCode": "AUD"
      }
    ]
  },
  {
    "symbol": "TAH",
    "displayName": "TABCORP HOLDINGS LIMITED",
    "industry": "Consumer Services",
    "dateListed": "1994-08-15",
    "marketCap": 2439040340,
    "xid": "264909",
    "priceChangeFiveDayPercent": 0.9389671361502356,
    "isRecentListing": false,
    "priceAsk": 1.085,
    "priceBid": 1.075,
    "priceChange": 0.004999999999999893,
    "priceChangePercent": 0.46728971962615823,
    "priceLast": 1.075,
    "sector": "Consumer Discretionary",
    "industryGroup": "Consumer Services",
    "securityType": 1,
    "volume": 2051354,
    "statusCode": "",
    "isin": "AU000000TAH8",
    "priceClose": 1.07,
    "priceDayHigh": 1.085,
    "priceDayLow": 1.07,
    "priceFiftyTwoWeekHigh": 5.53,
    "priceFiftyTwoWeekLow": 0.895,
    "volumeAverage": 11335474.835165,
    "dateExDate": "2022-08-31",
    "datePayDate": "2022-09-23",
    "dateRecordDate": "2022-09-01",
    "dividend": 0.065,
    "dividendType": "F",
    "frankingPercent": 100,
    "cashFlow": 254.7,
    "earningsPerShare": -0.05322,
    "freeCashFlowYield": 0.06855917410876503,
    "priceEarningsRatio": -99999.99,
    "priceToCash": 14.58594,
    "foreignExempt": false,
    "shareDescription": "Ordinary Fully Paid",
    "numOfShares": 2279476953,
    "yieldAnnual": 7.190697674418605,
    "incomeStatement": [
      {
        "revenue": 2373300000,
        "netIncome": 6775900000,
        "period": "2022A",
        "fPeriodEndDate": 44742,
        "curCode": "AUD"
      },
      {
        "revenue": 2479900000,
        "netIncome": 269400000,
        "period": "2021A",
        "fPeriodEndDate": 44377,
        "curCode": "AUD"
      },
      {
        "revenue": 5224000000,
        "netIncome": -870000000,
        "period": "2020A",
        "fPeriodEndDate": 44012,
        "curCode": "AUD"
      },
      {
        "revenue": 5488000000,
        "netIncome": 361000000,
        "period": "2019A",
        "fPeriodEndDate": 43646,
        "curCode": "AUD"
      }
    ]
  },
  {
    "symbol": "TLC",
    "displayName": "THE LOTTERY CORPORATION LIMITED",
    "industry": "Consumer Services",
    "dateListed": "2022-05-24",
    "marketCap": 9926941795,
    "xid": "722558151",
    "priceChangeFiveDayPercent": -0.6651884700665047,
    "isRecentListing": false,
    "priceAsk": 4.5200000000000005,
    "priceBid": 4.45,
    "priceChange": 0.020000000000000462,
    "priceChangePercent": 0.44843049327355294,
    "priceLast": 4.48,
    "sector": "Consumer Discretionary",
    "industryGroup": "Consumer Services",
    "securityType": 1,
    "volume": 2959982,
    "statusCode": "",
    "isin": "AU0000219529",
    "priceClose": 4.46,
    "priceDayHigh": 4.5200000000000005,
    "priceDayLow": 4.44,
    "priceFiftyTwoWeekHigh": 4.89,
    "priceFiftyTwoWeekLow": 3.905,
    "volumeAverage": 5514989.747253,
    "cashFlow": -99999.99,
    "earningsPerShare": 0.15572,
    "freeCashFlowYield": 0.04096693435827141,
    "priceEarningsRatio": 28.76959,
    "priceToCash": 24.40993,
    "foreignExempt": false,
    "shareDescription": "Ordinary Fully Paid",
    "numOfShares": 2225771703,
    "yieldAnnual": 0,
    "incomeStatement": [
      {
        "revenue": 3278600000,
        "netIncome": 346600000,
        "period": "2022A",
        "fPeriodEndDate": 44742,
        "curCode": "AUD"
      },
      {
        "revenue": 2951100000,
        "netIncome": 399300000,
        "period": "2021A",
        "fPeriodEndDate": 44377,
        "curCode": "AUD"
      },
      {
        "revenue": 2920000000,
        "netIncome": 450000000,
        "period": "2020A",
        "fPeriodEndDate": 44012,
        "curCode": "AUD"
      },
      {
        "revenue": 2868000000,
        "netIncome": 430000000,
        "period": "2019A",
        "fPeriodEndDate": 43646,
        "curCode": "AUD"
      }
    ]
  },
  {
    "symbol": "SGR",
    "displayName": "THE STAR ENTERTAINMENT GROUP LIMITED",
    "industry": "Consumer Services",
    "dateListed": "2011-06-06",
    "marketCap": 1708865507,
    "xid": "34171005",
    "priceChangeFiveDayPercent": -6.10079575596817,
    "isRecentListing": false,
    "priceAsk": 1.79,
    "priceBid": 1.7650000000000001,
    "priceChange": -0.02499999999999991,
    "priceChangePercent": -1.392757660167126,
    "priceLast": 1.77,
    "sector": "Consumer Discretionary",
    "industryGroup": "Consumer Services",
    "securityType": 1,
    "volume": 4889295,
    "statusCode": "",
    "isin": "AU000000SGR6",
    "priceClose": 1.795,
    "priceDayHigh": 1.81,
    "priceDayLow": 1.77,
    "priceFiftyTwoWeekHigh": 3.82,
    "priceFiftyTwoWeekLow": 1.765,
    "volumeAverage": 3566356.9,
    "dateExDate": "2020-02-25",
    "datePayDate": "2020-07-02",
    "dateRecordDate": "2020-02-26",
    "dividend": 0.105,
    "dividendType": "I",
    "frankingPercent": 100,
    "cashFlow": 33.4,
    "earningsPerShare": -0.21345,
    "freeCashFlowYield": 0.09987745036839799,
    "priceEarningsRatio": -99999.99,
    "priceToCash": 10.01227,
    "foreignExempt": false,
    "shareDescription": "Ordinary Fully Paid",
    "numOfShares": 952014210,
    "yieldAnnual": 0,
    "incomeStatement": [
      {
        "revenue": 1527100000,
        "netIncome": -202500000,
        "period": "2022A",
        "fPeriodEndDate": 44742,
        "curCode": "AUD"
      },
      {
        "revenue": 1545400000,
        "netIncome": 57900000,
        "period": "2021A",
        "fPeriodEndDate": 44377,
        "curCode": "AUD"
      },
      {
        "revenue": 1487000000,
        "netIncome": -94600000,
        "period": "2020A",
        "fPeriodEndDate": 44012,
        "curCode": "AUD"
      },
      {
        "revenue": 2158100000,
        "netIncome": 198000000,
        "period": "2019A",
        "fPeriodEndDate": 43646,
        "curCode": "AUD"
      }
    ]
  },
  {
    "symbol": "TCO",
    "displayName": "TRANSMETRO CORPORATION LIMITED",
    "industry": "Consumer Services",
    "dateListed": "1987-09-17",
    "marketCap": 15524022,
    "xid": "266012",
    "priceChangeFiveDayPercent": 0,
    "isRecentListing": false,
    "priceAsk": 1.98,
    "priceBid": 1.2,
    "priceChange": 0,
    "priceChangePercent": 0,
    "priceLast": 1.16,
    "sector": "Consumer Discretionary",
    "industryGroup": "Consumer Services",
    "securityType": 1,
    "volume": 0,
    "statusCode": "",
    "isin": "AU000000TCO0",
    "priceClose": 1.16,
    "priceFiftyTwoWeekHigh": 1.165,
    "priceFiftyTwoWeekLow": 0.98,
    "volumeAverage": 3160.8,
    "dateExDate": "2019-06-11",
    "datePayDate": "2019-06-28",
    "dateRecordDate": "2019-06-12",
    "dividend": 0.1,
    "dividendType": "F",
    "frankingPercent": 100,
    "cashFlow": 5.78545,
    "earningsPerShare": 0.25662,
    "freeCashFlowYield": 0.31367235040965613,
    "priceEarningsRatio": 4.5203,
    "priceToCash": 3.18804,
    "foreignExempt": false,
    "shareDescription": "Ordinary Fully Paid",
    "numOfShares": 13382778,
    "yieldAnnual": 0,
    "incomeStatement": [
      {
        "revenue": 16046960,
        "netIncome": 3326370,
        "period": "2022A",
        "fPeriodEndDate": 44742,
        "curCode": "AUD"
      },
      {
        "revenue": 14767970,
        "netIncome": -4405420,
        "period": "2021A",
        "fPeriodEndDate": 44377,
        "curCode": "AUD"
      },
      {
        "revenue": 22610860,
        "netIncome": -876810,
        "period": "2020A",
        "fPeriodEndDate": 44012,
        "curCode": "AUD"
      },
      {
        "revenue": 28408480,
        "netIncome": 5461580,
        "period": "2019A",
        "fPeriodEndDate": 43646,
        "curCode": "AUD"
      }
    ]
  },
  {
    "symbol": "VVA",
    "displayName": "VIVA LEISURE LIMITED",
    "industry": "Consumer Services",
    "dateListed": "2019-06-07",
    "marketCap": 101120379,
    "xid": "537673599",
    "priceChangeFiveDayPercent": -3.9473684210526256,
    "isRecentListing": false,
    "priceAsk": 1.1400000000000001,
    "priceBid": 1.09,
    "priceChange": -0.025000000000000133,
    "priceChangePercent": -2.2321428571428688,
    "priceLast": 1.095,
    "sector": "Consumer Discretionary",
    "industryGroup": "Consumer Services",
    "securityType": 1,
    "volume": 6521,
    "statusCode": "",
    "isin": "AU0000046013",
    "priceClose": 1.12,
    "priceDayHigh": 1.12,
    "priceDayLow": 1.09,
    "priceFiftyTwoWeekHigh": 2.2,
    "priceFiftyTwoWeekLow": 1.05,
    "volumeAverage": 107745.193182,
    "cashFlow": 15.52221,
    "earningsPerShare": -0.13943,
    "freeCashFlowYield": 0.2649701511124772,
    "priceEarningsRatio": -99999.99,
    "priceToCash": 3.77401,
    "foreignExempt": false,
    "shareDescription": "Ordinary Fully Paid",
    "numOfShares": 90286053,
    "yieldAnnual": 0,
    "incomeStatement": [
      {
        "revenue": 90762640,
        "netIncome": -12141190,
        "period": "2022A",
        "fPeriodEndDate": 44742,
        "curCode": "AUD"
      },
      {
        "revenue": 83595660,
        "netIncome": -6384900,
        "period": "2021A",
        "fPeriodEndDate": 44377,
        "curCode": "AUD"
      },
      {
        "revenue": 40367120,
        "netIncome": -6246350,
        "period": "2020A",
        "fPeriodEndDate": 44012,
        "curCode": "AUD"
      },
      {
        "revenue": 31105640,
        "netIncome": 2855100,
        "period": "2019A",
        "fPeriodEndDate": 43646,
        "curCode": "AUD"
      }
    ]
  },
  {
    "symbol": "XRG",
    "displayName": "XREALITY GROUP LTD",
    "industry": "Consumer Services",
    "dateListed": "2013-01-18",
    "marketCap": 24562401,
    "xid": "52015058",
    "priceChangeFiveDayPercent": -4.999999999999994,
    "isRecentListing": false,
    "priceAsk": 0.062,
    "priceBid": 0.055,
    "priceChange": -0.0010000000000000009,
    "priceChangePercent": -1.7241379310344842,
    "priceLast": 0.057,
    "sector": "Consumer Discretionary",
    "industryGroup": "Consumer Services",
    "securityType": 1,
    "volume": 187046,
    "statusCode": "",
    "isin": "AU0000196065",
    "priceClose": 0.058,
    "priceDayHigh": 0.061,
    "priceDayLow": 0.057,
    "priceFiftyTwoWeekHigh": 0.091,
    "priceFiftyTwoWeekLow": 0.027,
    "volumeAverage": 349108.137931,
    "cashFlow": -0.75511,
    "earningsPerShare": -0.01991,
    "freeCashFlowYield": -0.0000100000010000001,
    "priceEarningsRatio": -99999.99,
    "priceToCash": -99999.99,
    "foreignExempt": false,
    "shareDescription": "Ordinary Fully Paid",
    "numOfShares": 423489675,
    "yieldAnnual": 0,
    "incomeStatement": [
      {
        "revenue": 6574710,
        "netIncome": -6932210,
        "period": "2022A",
        "fPeriodEndDate": 44742,
        "curCode": "AUD"
      },
      {
        "revenue": 7265180,
        "netIncome": 4062460,
        "period": "2021A",
        "fPeriodEndDate": 44377,
        "curCode": "AUD"
      },
      {
        "revenue": 5002090,
        "netIncome": -5440250,
        "period": "2020A",
        "fPeriodEndDate": 44012,
        "curCode": "AUD"
      },
      {
        "revenue": 7507200,
        "netIncome": -7401000,
        "period": "2019A",
        "fPeriodEndDate": 43646,
        "curCode": "AUD"
      }
    ]
  }
]